<?xml version='1.0' encoding='utf-8'?>
<linkGrp toDoc='toh144.en.xml' fromDoc='toh144.bo.xml'>
<link type='0-1' xtargets=';1:1' status='man'/>
<link type='1-1' xtargets='1:1;1:2' status='man'/>
<link type='0-1' xtargets=';1:3' status='man'/>
<link type='1-0' xtargets='2:1;' status='man'/>
<link type='1-1' xtargets='3:1;1:4' status='man'/>
<link type='1-1' xtargets='4:1;2:1' status='man'/>
<link type='1-1' xtargets='4:2;3:1' status='man'/>
<link type='1-1' xtargets='4:3;4:1' status='man'/>
<link type='1-1' xtargets='4:4;4:2' status='man'/>
<link type='1-1' xtargets='4:5;4:3' status='man'/>
<link type='1-1' xtargets='4:6;4:4' status='man'/>
<link type='1-1' xtargets='4:7;4:5' status='man'/>
<link type='1-1' xtargets='4:8;4:6' status='man'/>
<link type='1-1' xtargets='4:9;4:7' status='man'/>
<link type='1-1' xtargets='4:10;4:8' status='man'/>
<link type='1-1' xtargets='4:11;4:9' status='man'/>
<link type='1-1' xtargets='4:12;4:10' status='man'/>
<link type='1-1' xtargets='4:13;4:11' status='man'/>
<link type='1-1' xtargets='5:1;5:1' status='man'/>
<link type='1-1' xtargets='5:2;5:2' status='man'/>
<link type='1-1' xtargets='5:3;6:1' status='man'/>
<link type='1-1' xtargets='5:4;6:2' status='man'/>
<link type='1-1' xtargets='6:1;7:1' status='man'/>
<link type='1-1' xtargets='6:2;8:1' status='man'/>
<link type='1-1' xtargets='6:3;9:1' status='man'/>
<link type='1-1' xtargets='6:4;10:1' status='man'/>
<link type='1-1' xtargets='7:1;11:1' status='man'/>
<link type='1-1' xtargets='7:2;12:1' status='man'/>
<link type='1-1' xtargets='7:3;13:1' status='man'/>
<link type='0-1' xtargets=';14:1' status='man'/>
<link type='1-1' xtargets='7:4;15:1' status='man'/>
<link type='1-1' xtargets='7:5;15:2' status='man'/>
<link type='1-1' xtargets='7:6;15:3' status='man'/>
<link type='1-1' xtargets='7:7;16:1' status='man'/>
<link type='1-1' xtargets='8:1;17:1' status='man'/>
<link type='1-1' xtargets='8:2;17:2' status='man'/>
<link type='1-1' xtargets='8:3;18:1' status='man'/>
<link type='1-0' xtargets='9:1;' status='man'/>
<link type='1-1' xtargets='10:1;19:1' status='man'/>
<link type='1-1' xtargets='10:2;20:1' status='man'/>
<link type='1-1' xtargets='10:3;20:2' status='man'/>
<link type='1-0' xtargets='11:1;' status='man'/>
<link type='1-1' xtargets='12:1;21:1' status='man'/>
<link type='1-1' xtargets='12:2;21:2' status='man'/>
<link type='1-1' xtargets='13:1;21:3' status='man'/>
<link type='1-1' xtargets='13:2;21:4' status='man'/>
<link type='1-1' xtargets='13:3;22:1' status='man'/>
<link type='0-1' xtargets=';23:1' status='man'/>
<link type='1-1' xtargets='13:4;23:2' status='man'/>
<link type='1-1' xtargets='14:1;24:1' status='man'/>
<link type='1-1' xtargets='14:2;25:1' status='man'/>
<link type='1-1' xtargets='14:3;26:1' status='man'/>
<link type='1-1' xtargets='14:4;27:1' status='man'/>
<link type='1-1' xtargets='15:1;28:1' status='man'/>
<link type='1-1' xtargets='15:2;28:2' status='man'/>
<link type='1-1' xtargets='15:3;28:3' status='man'/>
<link type='1-1' xtargets='16:1;28:4' status='man'/>
<link type='1-1' xtargets='16:2;28:5' status='man'/>
<link type='1-1' xtargets='16:3;28:6' status='man'/>
<link type='1-1' xtargets='16:4;29:1' status='man'/>
<link type='1-1' xtargets='16:5;30:1' status='man'/>
<link type='1-1' xtargets='16:6;31:1' status='man'/>
<link type='1-1' xtargets='16:7;32:1' status='man'/>
<link type='1-1' xtargets='16:8;33:1' status='man'/>
<link type='1-0' xtargets='17:1;' status='man'/>
<link type='1-1' xtargets='18:1;34:1' status='man'/>
<link type='1-1' xtargets='18:2;34:2' status='man'/>
<link type='1-1' xtargets='19:1;34:3' status='man'/>
<link type='1-1' xtargets='19:2;34:4' status='man'/>
<link type='1-1' xtargets='19:3;35:1' status='man'/>
<link type='1-1' xtargets='19:4;35:2' status='man'/>
<link type='1-1' xtargets='19:5;36:1' status='man'/>
<link type='1-1' xtargets='19:6;37:1' status='man'/>
<link type='1-1' xtargets='19:7;37:2' status='man'/>
<link type='1-1' xtargets='20:1;38:1' status='man'/>
<link type='1-1' xtargets='20:2;39:1' status='man'/>
<link type='1-1' xtargets='20:3;40:1' status='man'/>
<link type='1-1' xtargets='20:4;41:1' status='man'/>
<link type='1-1' xtargets='20:5;42:1' status='man'/>
<link type='1-1' xtargets='20:6;43:1' status='man'/>
<link type='1-1' xtargets='20:7;44:1' status='man'/>
<link type='1-1' xtargets='20:8;45:1' status='man'/>
<link type='1-1' xtargets='21:1;46:1' status='man'/>
<link type='1-1' xtargets='21:2;47:1' status='man'/>
<link type='1-1' xtargets='21:3;48:1' status='man'/>
<link type='1-1' xtargets='21:4;48:2' status='man'/>
<link type='1-1' xtargets='21:5;49:1' status='man'/>
<link type='1-1' xtargets='22:1;50:1' status='man'/>
<link type='1-1' xtargets='22:2;50:2' status='man'/>
<link type='1-1' xtargets='22:3;50:3' status='man'/>
<link type='1-1' xtargets='22:4;50:4' status='man'/>
<link type='1-1' xtargets='22:5;50:5' status='man'/>
<link type='1-1' xtargets='22:6;50:6' status='man'/>
<link type='1-1' xtargets='22:7;50:7' status='man'/>
<link type='1-1' xtargets='22:8;50:8' status='man'/>
<link type='1-1' xtargets='22:9;51:1' status='man'/>
<link type='1-1' xtargets='22:10;52:1' status='man'/>
<link type='1-0' xtargets='23:1;' status='man'/>
<link type='1-1' xtargets='24:1;53:1' status='man'/>
<link type='1-1' xtargets='24:2;53:2' status='man'/>
<link type='1-1' xtargets='25:1;54:1' status='man'/>
<link type='1-1' xtargets='25:2;55:1' status='man'/>
<link type='1-1' xtargets='26:1;55:2' status='man'/>
<link type='1-1' xtargets='26:2;55:3' status='man'/>
<link type='0-1' xtargets=';56:1' status='man'/>
<link type='1-1' xtargets='26:3;56:2' status='man'/>
<link type='1-1' xtargets='27:1;57:1' status='man'/>
<link type='1-1' xtargets='27:2;57:2' status='man'/>
<link type='1-1' xtargets='28:1;57:3' status='man'/>
<link type='1-1' xtargets='28:2;57:4' status='man'/>
<link type='1-1' xtargets='28:3;58:1' status='man'/>
<link type='1-1' xtargets='28:4;58:2' status='man'/>
<link type='1-1' xtargets='28:5;59:1' status='man'/>
<link type='1-1' xtargets='28:6;60:1' status='man'/>
<link type='1-1' xtargets='28:7;61:1' status='man'/>
<link type='1-1' xtargets='28:8;62:1' status='man'/>
<link type='1-1' xtargets='28:9;63:1' status='man'/>
<link type='1-1' xtargets='29:1;64:1' status='man'/>
<link type='1-1' xtargets='29:2;64:2' status='man'/>
<link type='1-1' xtargets='30:1;64:3' status='man'/>
<link type='1-1' xtargets='30:2;64:4' status='man'/>
<link type='1-1' xtargets='31:1;65:1' status='man'/>
<link type='1-1' xtargets='31:2;65:2' status='man'/>
<link type='1-1' xtargets='32:1;65:3' status='man'/>
<link type='1-1' xtargets='32:2;65:4' status='man'/>
<link type='1-1' xtargets='33:1;66:1' status='man'/>
<link type='1-1' xtargets='33:2;66:2' status='man'/>
<link type='1-1' xtargets='34:1;66:3' status='man'/>
<link type='1-1' xtargets='34:2;66:4' status='man'/>
<link type='1-1' xtargets='35:1;67:1' status='man'/>
<link type='1-1' xtargets='36:1;68:1' status='man'/>
<link type='1-1' xtargets='36:2;68:2' status='man'/>
<link type='1-1' xtargets='37:1;68:3' status='man'/>
<link type='1-1' xtargets='37:2;68:4' status='man'/>
<link type='1-1' xtargets='37:3;69:1' status='man'/>
<link type='1-1' xtargets='37:4;70:1' status='man'/>
<link type='1-1' xtargets='37:5;71:1' status='man'/>
<link type='1-1' xtargets='37:6;72:1' status='man'/>
<link type='1-1' xtargets='37:7;72:2' status='man'/>
<link type='1-1' xtargets='37:8;73:1' status='man'/>
<link type='1-1' xtargets='38:1;74:1' status='man'/>
<link type='1-0' xtargets='39:1;' status='man'/>
<link type='1-1' xtargets='40:1;75:1' status='man'/>
<link type='1-1' xtargets='40:2;75:2' status='man'/>
<link type='1-1' xtargets='41:1;75:3' status='man'/>
<link type='1-1' xtargets='41:2;75:4' status='man'/>
<link type='1-1' xtargets='41:3;76:1' status='man'/>
<link type='0-1' xtargets=';76:2' status='man'/>
<link type='1-1' xtargets='41:4;76:3' status='man'/>
<link type='1-1' xtargets='41:5;76:4' status='man'/>
<link type='1-1' xtargets='41:6;77:1' status='man'/>
<link type='1-1' xtargets='41:7;77:2' status='man'/>
<link type='1-1' xtargets='41:8;77:3' status='man'/>
<link type='1-1' xtargets='41:9;77:4' status='man'/>
<link type='1-1' xtargets='41:10;78:1' status='man'/>
<link type='1-1' xtargets='41:11;78:2' status='man'/>
<link type='1-1' xtargets='42:1;79:1' status='man'/>
<link type='1-1' xtargets='42:2;79:2' status='man'/>
<link type='1-1' xtargets='42:3;80:1' status='man'/>
<link type='1-1' xtargets='42:4;81:1' status='man'/>
<link type='1-1' xtargets='42:5;82:1' status='man'/>
<link type='1-1' xtargets='42:6;83:1' status='man'/>
<link type='1-1' xtargets='42:7;84:1' status='man'/>
<link type='1-1' xtargets='42:8;85:1' status='man'/>
<link type='1-1' xtargets='42:9;86:1' status='man'/>
<link type='1-1' xtargets='43:1;87:1' status='man'/>
<link type='1-1' xtargets='43:2;88:1' status='man'/>
<link type='1-1' xtargets='43:3;89:1' status='man'/>
<link type='1-1' xtargets='43:4;90:1' status='man'/>
<link type='1-1' xtargets='43:5;91:1' status='man'/>
<link type='1-1' xtargets='43:6;92:1' status='man'/>
<link type='1-1' xtargets='44:1;93:1' status='man'/>
<link type='1-1' xtargets='44:2;94:1' status='man'/>
<link type='1-1' xtargets='45:1;95:1' status='man'/>
<link type='1-1' xtargets='45:2;95:2' status='man'/>
<link type='1-1' xtargets='45:3;96:1' status='man'/>
<link type='1-1' xtargets='46:1;97:1' status='man'/>
<link type='1-1' xtargets='46:2;98:1' status='man'/>
<link type='1-1' xtargets='46:3;99:1' status='man'/>
<link type='1-1' xtargets='46:4;99:2' status='man'/>
<link type='1-1' xtargets='46:5;99:3' status='man'/>
<link type='1-1' xtargets='46:6;100:1' status='man'/>
<link type='1-1' xtargets='47:1;101:1' status='man'/>
<link type='1-1' xtargets='47:2;101:2' status='man'/>
<link type='1-1' xtargets='48:1;102:1' status='man'/>
<link type='1-1' xtargets='48:2;102:2' status='man'/>
<link type='1-1' xtargets='48:3;103:1' status='man'/>
<link type='1-1' xtargets='48:4;104:1' status='man'/>
<link type='1-1' xtargets='48:5;105:1' status='man'/>
<link type='1-1' xtargets='48:6;106:1' status='man'/>
<link type='1-1' xtargets='48:7;106:2' status='man'/>
<link type='1-0' xtargets='49:1;' status='man'/>
<link type='1-1' xtargets='50:1;107:1' status='man'/>
<link type='1-1' xtargets='50:2;107:2' status='man'/>
<link type='1-1' xtargets='51:1;107:3' status='man'/>
<link type='1-1' xtargets='51:2;107:4' status='man'/>
<link type='1-1' xtargets='51:3;108:1' status='man'/>
<link type='1-1' xtargets='51:4;108:2' status='man'/>
<link type='1-1' xtargets='51:5;109:1' status='man'/>
<link type='1-1' xtargets='51:6;110:1' status='man'/>
<link type='1-1' xtargets='51:7;110:2' status='man'/>
<link type='1-1' xtargets='52:1;111:1' status='man'/>
<link type='1-1' xtargets='52:2;112:1' status='man'/>
<link type='1-1' xtargets='52:3;112:2' status='man'/>
<link type='1-1' xtargets='52:4;113:1' status='man'/>
<link type='1-1' xtargets='52:5;114:1' status='man'/>
<link type='1-1' xtargets='52:6;115:1' status='man'/>
<link type='1-1' xtargets='53:1;116:1' status='man'/>
<link type='1-1' xtargets='53:2;116:2' status='man'/>
<link type='1-1' xtargets='53:3;117:1' status='man'/>
<link type='1-1' xtargets='53:4;118:1' status='man'/>
<link type='1-1' xtargets='53:5;118:2' status='man'/>
<link type='1-1' xtargets='53:6;118:3' status='man'/>
<link type='1-1' xtargets='53:7;118:4' status='man'/>
<link type='1-1' xtargets='53:8;118:5' status='man'/>
<link type='1-1' xtargets='54:1;119:1' status='man'/>
<link type='1-1' xtargets='54:2;120:1' status='man'/>
<link type='1-1' xtargets='54:3;121:1' status='man'/>
<link type='1-1' xtargets='54:4;121:2' status='man'/>
<link type='1-1' xtargets='54:5;122:1' status='man'/>
<link type='1-1' xtargets='54:6;123:1' status='man'/>
<link type='1-1' xtargets='54:7;124:1' status='man'/>
<link type='1-1' xtargets='54:8;125:1' status='man'/>
<link type='1-0' xtargets='55:1;' status='man'/>
<link type='1-1' xtargets='56:1;126:1' status='man'/>
<link type='1-1' xtargets='56:2;126:2' status='man'/>
<link type='1-1' xtargets='57:1;126:3' status='man'/>
<link type='1-1' xtargets='57:2;126:4' status='man'/>
<link type='1-1' xtargets='58:1;127:1' status='man'/>
<link type='1-1' xtargets='58:2;127:2' status='man'/>
<link type='1-1' xtargets='59:1;127:3' status='man'/>
<link type='1-1' xtargets='59:2;127:4' status='man'/>
<link type='1-1' xtargets='59:3;127:5' status='man'/>
<link type='1-1' xtargets='59:4;128:1' status='man'/>
<link type='1-1' xtargets='59:5;129:1' status='man'/>
<link type='1-1' xtargets='59:6;129:2' status='man'/>
<link type='1-1' xtargets='59:7;130:1' status='man'/>
<link type='1-1' xtargets='60:1;131:1' status='man'/>
<link type='1-1' xtargets='60:2;131:2' status='man'/>
<link type='1-1' xtargets='60:3;131:3' status='man'/>
<link type='1-1' xtargets='60:4;131:4' status='man'/>
<link type='1-1' xtargets='61:1;132:1' status='man'/>
<link type='1-1' xtargets='61:2;132:2' status='man'/>
<link type='1-1' xtargets='61:3;133:1' status='man'/>
<link type='1-1' xtargets='61:4;134:1' status='man'/>
<link type='1-1' xtargets='61:5;135:1' status='man'/>
<link type='1-1' xtargets='61:6;135:2' status='man'/>
<link type='1-1' xtargets='61:7;136:1' status='man'/>
<link type='1-1' xtargets='62:1;137:1' status='man'/>
<link type='1-1' xtargets='62:2;137:2' status='man'/>
<link type='1-1' xtargets='62:3;137:3' status='man'/>
<link type='1-1' xtargets='63:1;137:4' status='man'/>
<link type='1-1' xtargets='63:2;137:5' status='man'/>
<link type='1-1' xtargets='63:3;138:1' status='man'/>
<link type='1-1' xtargets='63:4;139:1' status='man'/>
<link type='1-1' xtargets='63:5;140:1' status='man'/>
<link type='1-1' xtargets='63:6;141:1' status='man'/>
<link type='1-1' xtargets='63:7;142:1' status='man'/>
<link type='1-1' xtargets='63:8;143:1' status='man'/>
<link type='1-0' xtargets='64:1;' status='man'/>
<link type='1-1' xtargets='65:1;144:1' status='man'/>
<link type='1-1' xtargets='65:2;144:2' status='man'/>
<link type='1-1' xtargets='66:1;144:3' status='man'/>
<link type='1-1' xtargets='66:2;144:4' status='man'/>
<link type='1-1' xtargets='66:3;144:5' status='man'/>
<link type='1-1' xtargets='66:4;145:1' status='man'/>
<link type='1-1' xtargets='66:5;145:2' status='man'/>
<link type='1-1' xtargets='66:6;145:3' status='man'/>
<link type='1-1' xtargets='66:7;146:1' status='man'/>
<link type='1-1' xtargets='66:8;147:1' status='man'/>
<link type='1-1' xtargets='66:9;148:1' status='man'/>
<link type='1-0' xtargets='67:1;' status='man'/>
<link type='1-1' xtargets='68:1;149:1' status='man'/>
<link type='1-1' xtargets='68:2;149:2' status='man'/>
<link type='1-1' xtargets='69:1;149:3' status='man'/>
<link type='1-1' xtargets='69:2;149:4' status='man'/>
<link type='0-1' xtargets=';150:1' status='man'/>
<link type='1-1' xtargets='69:3;150:2' status='man'/>
<link type='1-1' xtargets='69:4;150:3' status='man'/>
<link type='1-1' xtargets='69:5;150:4' status='man'/>
<link type='1-1' xtargets='69:6;150:5' status='man'/>
<link type='1-1' xtargets='69:7;150:6' status='man'/>
<link type='1-1' xtargets='69:8;150:7' status='man'/>
<link type='1-1' xtargets='69:9;150:8' status='man'/>
<link type='1-1' xtargets='70:1;151:1' status='man'/>
<link type='1-1' xtargets='70:2;152:1' status='man'/>
<link type='1-1' xtargets='70:3;153:1' status='man'/>
<link type='1-1' xtargets='70:4;153:2' status='man'/>
<link type='1-1' xtargets='70:5;154:1' status='man'/>
<link type='1-0' xtargets='71:1;' status='man'/>
<link type='1-1' xtargets='72:1;155:1' status='man'/>
<link type='1-1' xtargets='72:2;155:2' status='man'/>
<link type='1-1' xtargets='73:1;155:3' status='man'/>
<link type='1-1' xtargets='73:2;155:4' status='man'/>
<link type='0-1' xtargets=';156:1' status='man'/>
<link type='1-1' xtargets='73:3;156:2' status='man'/>
<link type='1-1' xtargets='73:4;157:1' status='man'/>
<link type='1-1' xtargets='73:5;158:1' status='man'/>
<link type='1-1' xtargets='73:6;158:2' status='man'/>
<link type='1-1' xtargets='73:7;159:1' status='man'/>
<link type='1-1' xtargets='73:8;160:1' status='man'/>
<link type='1-1' xtargets='73:9;161:1' status='man'/>
<link type='1-1' xtargets='73:10;162:1' status='man'/>
<link type='1-0' xtargets='74:1;' status='man'/>
<link type='1-1' xtargets='75:1;163:1' status='man'/>
<link type='1-1' xtargets='75:2;163:2' status='man'/>
<link type='1-1' xtargets='76:1;163:3' status='man'/>
<link type='1-1' xtargets='76:2;163:4' status='man'/>
<link type='1-1' xtargets='76:3;163:5' status='man'/>
<link type='1-1' xtargets='76:4;164:1' status='man'/>
<link type='1-1' xtargets='76:5;165:1' status='man'/>
<link type='1-1' xtargets='76:6;165:2' status='man'/>
<link type='1-1' xtargets='76:7;166:1' status='man'/>
<link type='1-0' xtargets='77:1;' status='man'/>
<link type='1-1' xtargets='78:1;167:1' status='man'/>
<link type='1-1' xtargets='78:2;167:2' status='man'/>
<link type='1-1' xtargets='79:1;167:3' status='man'/>
<link type='1-1' xtargets='79:2;167:4' status='man'/>
<link type='1-1' xtargets='79:3;168:1' status='man'/>
<link type='1-1' xtargets='80:1;169:1' status='man'/>
<link type='1-1' xtargets='80:2;170:1' status='man'/>
<link type='1-1' xtargets='81:1;171:1' status='man'/>
<link type='1-1' xtargets='81:2;172:1' status='man'/>
<link type='1-1' xtargets='81:3;172:2' status='man'/>
<link type='1-1' xtargets='81:4;172:3' status='man'/>
<link type='1-1' xtargets='81:5;172:4' status='man'/>
<link type='1-1' xtargets='81:6;172:5' status='man'/>
<link type='1-1' xtargets='82:1;173:1' status='man'/>
<link type='1-1' xtargets='82:2;174:1' status='man'/>
<link type='1-1' xtargets='82:3;175:1' status='man'/>
<link type='1-1' xtargets='82:4;176:1' status='man'/>
<link type='1-1' xtargets='82:5;177:1' status='man'/>
<link type='1-1' xtargets='83:1;178:1' status='man'/>
<link type='1-1' xtargets='83:2;179:1' status='man'/>
<link type='1-1' xtargets='83:3;180:1' status='man'/>
<link type='1-1' xtargets='84:1;181:1' status='man'/>
<link type='1-1' xtargets='84:2;182:1' status='man'/>
<link type='1-1' xtargets='84:3;183:1' status='man'/>
<link type='1-1' xtargets='84:4;184:1' status='man'/>
<link type='1-1' xtargets='85:1;185:1' status='man'/>
<link type='1-1' xtargets='86:1;186:1' status='man'/>
<link type='1-0' xtargets='87:1;' status='man'/>
<link type='1-1' xtargets='88:1;187:1' status='man'/>
<link type='1-1' xtargets='88:2;188:1' status='man'/>
<link type='1-1' xtargets='89:1;188:2' status='man'/>
<link type='1-1' xtargets='89:2;188:3' status='man'/>
<link type='0-1' xtargets=';189:1' status='man'/>
<link type='1-1' xtargets='89:3;189:2' status='man'/>
<link type='1-0' xtargets='90:1;' status='man'/>
<link type='1-1' xtargets='91:1;190:1' status='man'/>
<link type='1-1' xtargets='91:2;190:2' status='man'/>
<link type='1-1' xtargets='92:1;190:3' status='man'/>
<link type='1-1' xtargets='92:2;190:4' status='man'/>
<link type='1-1' xtargets='92:3;191:1' status='man'/>
<link type='1-1' xtargets='92:4;192:1' status='man'/>
<link type='1-1' xtargets='92:5;193:1' status='man'/>
<link type='1-1' xtargets='92:6;194:1' status='man'/>
<link type='1-1' xtargets='92:7;194:2' status='man'/>
<link type='1-1' xtargets='93:1;195:1' status='man'/>
<link type='1-1' xtargets='93:2;195:2' status='man'/>
<link type='1-1' xtargets='93:3;196:1' status='man'/>
<link type='1-1' xtargets='93:4;197:1' status='man'/>
<link type='1-1' xtargets='93:5;198:1' status='man'/>
<link type='1-0' xtargets='94:1;' status='man'/>
<link type='1-1' xtargets='95:1;199:1' status='man'/>
<link type='1-1' xtargets='95:2;199:2' status='man'/>
<link type='1-1' xtargets='96:1;199:3' status='man'/>
<link type='1-1' xtargets='96:2;199:4' status='man'/>
<link type='1-1' xtargets='96:3;200:1' status='man'/>
<link type='1-1' xtargets='96:4;200:2' status='man'/>
<link type='1-1' xtargets='96:5;200:3' status='man'/>
<link type='2-2' xtargets='96:6 96:7;200:4 200:5' status='man'/>
<link type='1-1' xtargets='96:8;200:6' status='man'/>
<link type='1-1' xtargets='96:9;201:1' status='man'/>
<link type='1-0' xtargets='97:1;' status='man'/>
<link type='1-1' xtargets='98:1;202:1' status='man'/>
<link type='1-1' xtargets='98:2;202:2' status='man'/>
<link type='1-1' xtargets='99:1;202:3' status='man'/>
<link type='1-1' xtargets='99:2;202:4' status='man'/>
<link type='1-1' xtargets='99:3;202:5' status='man'/>
<link type='1-1' xtargets='99:4;203:1' status='man'/>
<link type='1-1' xtargets='99:5;203:2' status='man'/>
<link type='1-1' xtargets='100:1;204:1' status='man'/>
<link type='1-1' xtargets='100:2;205:1' status='man'/>
<link type='1-1' xtargets='100:3;205:2' status='man'/>
<link type='1-1' xtargets='101:1;206:1' status='man'/>
<link type='1-2' xtargets='101:2;207:1 208:1' status='man'/>
<link type='1-2' xtargets='101:3;208:2 208:3' status='man'/>
<link type='1-1' xtargets='101:4;208:4' status='man'/>
<link type='1-1' xtargets='101:5;209:1' status='man'/>
<link type='1-1' xtargets='101:6;210:1' status='man'/>
<link type='1-1' xtargets='102:1;211:1' status='man'/>
<link type='1-1' xtargets='102:2;212:1' status='man'/>
<link type='1-1' xtargets='102:3;213:1' status='man'/>
<link type='1-1' xtargets='103:1;214:1' status='man'/>
<link type='1-1' xtargets='103:2;214:2' status='man'/>
<link type='1-1' xtargets='103:3;214:3' status='man'/>
<link type='1-1' xtargets='103:4;215:1' status='man'/>
<link type='1-1' xtargets='103:5;216:1' status='man'/>
<link type='1-1' xtargets='103:6;217:1' status='man'/>
<link type='1-1' xtargets='104:1;218:1' status='man'/>
<link type='1-1' xtargets='104:2;219:1' status='man'/>
<link type='1-1' xtargets='105:1;220:1' status='man'/>
<link type='1-1' xtargets='105:2;220:2' status='man'/>
<link type='1-1' xtargets='105:3;221:1' status='man'/>
<link type='2-2' xtargets='106:1 106:2;222:1 222:2' status='man'/>
<link type='1-1' xtargets='106:3;222:3' status='man'/>
<link type='1-1' xtargets='106:4;223:1' status='man'/>
<link type='1-1' xtargets='107:1;224:1' status='man'/>
<link type='1-1' xtargets='107:2;224:2' status='man'/>
<link type='1-1' xtargets='107:3;225:1' status='man'/>
<link type='1-1' xtargets='108:1;226:1' status='man'/>
<link type='1-1' xtargets='108:2;227:1' status='man'/>
<link type='1-1' xtargets='108:3;228:1' status='man'/>
<link type='2-2' xtargets='109:1 109:2;229:1 230:1' status='man'/>
<link type='1-1' xtargets='109:3;231:1' status='man'/>
<link type='1-1' xtargets='110:1;232:1' status='man'/>
<link type='1-1' xtargets='111:1;233:1' status='man'/>
<link type='1-1' xtargets='111:2;234:1' status='man'/>
<link type='1-1' xtargets='111:3;234:2' status='man'/>
<link type='1-1' xtargets='111:4;235:1' status='man'/>
<link type='1-1' xtargets='111:5;235:2' status='man'/>
<link type='1-1' xtargets='111:6;236:1' status='man'/>
<link type='1-1' xtargets='112:1;237:1' status='man'/>
<link type='1-1' xtargets='112:2;238:1' status='man'/>
<link type='1-1' xtargets='112:3;239:1' status='man'/>
<link type='1-1' xtargets='113:1;240:1' status='man'/>
<link type='1-1' xtargets='113:2;241:1' status='man'/>
<link type='1-1' xtargets='114:1;242:1' status='man'/>
<link type='1-1' xtargets='114:2;243:1' status='man'/>
<link type='1-1' xtargets='114:3;244:1' status='man'/>
<link type='1-1' xtargets='114:4;245:1' status='man'/>
<link type='1-1' xtargets='114:5;246:1' status='man'/>
<link type='1-1' xtargets='115:1;247:1' status='man'/>
<link type='1-1' xtargets='115:2;248:1' status='man'/>
<link type='1-1' xtargets='116:1;249:1' status='man'/>
<link type='1-1' xtargets='116:2;249:2' status='man'/>
<link type='1-1' xtargets='116:3;250:1' status='man'/>
<link type='1-1' xtargets='117:1;251:1' status='man'/>
<link type='1-1' xtargets='117:2;252:1' status='man'/>
<link type='1-1' xtargets='118:1;253:1' status='man'/>
<link type='1-1' xtargets='118:2;254:1' status='man'/>
<link type='1-1' xtargets='118:3;255:1' status='man'/>
<link type='1-1' xtargets='118:4;256:1' status='man'/>
<link type='1-1' xtargets='118:5;257:1' status='man'/>
<link type='2-2' xtargets='119:1 119:2;258:1 259:1' status='man'/>
<link type='1-1' xtargets='119:3;260:1' status='man'/>
<link type='1-1' xtargets='119:4;261:1' status='man'/>
<link type='2-2' xtargets='120:1 120:2;262:1 262:2' status='man'/>
<link type='1-1' xtargets='120:3;263:1' status='man'/>
<link type='1-1' xtargets='121:1;264:1' status='man'/>
<link type='1-1' xtargets='121:2;264:2' status='man'/>
<link type='1-1' xtargets='121:3;265:1' status='man'/>
<link type='1-1' xtargets='122:1;266:1' status='man'/>
<link type='1-1' xtargets='122:2;267:1' status='man'/>
<link type='1-1' xtargets='123:1;268:1' status='man'/>
<link type='1-1' xtargets='123:2;268:2' status='man'/>
<link type='1-1' xtargets='123:3;269:1' status='man'/>
<link type='1-1' xtargets='124:1;270:1' status='man'/>
<link type='1-1' xtargets='125:1;271:1' status='man'/>
<link type='1-1' xtargets='125:2;272:1' status='man'/>
<link type='1-1' xtargets='125:3;272:2' status='man'/>
<link type='1-1' xtargets='125:4;273:1' status='man'/>
<link type='1-1' xtargets='125:5;274:1' status='man'/>
<link type='1-1' xtargets='125:6;274:2' status='man'/>
<link type='1-1' xtargets='125:7;274:3' status='man'/>
<link type='1-1' xtargets='126:1;275:1' status='man'/>
<link type='1-1' xtargets='126:2;276:1' status='man'/>
<link type='1-1' xtargets='126:3;277:1' status='man'/>
<link type='1-1' xtargets='127:1;278:1' status='man'/>
<link type='1-1' xtargets='127:2;279:1' status='man'/>
<link type='1-1' xtargets='127:3;280:1' status='man'/>
<link type='1-1' xtargets='127:4;281:1' status='man'/>
<link type='1-1' xtargets='128:1;282:1' status='man'/>
<link type='1-0' xtargets='129:1;' status='man'/>
<link type='0-1' xtargets=';283:1' status='man'/>
<link type='1-1' xtargets='130:1;283:2' status='man'/>
<link type='1-1' xtargets='130:2;283:3' status='man'/>
<link type='1-1' xtargets='131:1;283:4' status='man'/>
<link type='1-1' xtargets='131:2;283:5' status='man'/>
<link type='1-1' xtargets='131:3;284:1' status='man'/>
<link type='1-1' xtargets='131:4;284:2' status='man'/>
<link type='1-1' xtargets='131:5;285:1' status='man'/>
<link type='1-1' xtargets='131:6;286:1' status='man'/>
<link type='1-0' xtargets='132:1;' status='man'/>
<link type='1-1' xtargets='133:1;287:1' status='man'/>
<link type='1-1' xtargets='133:2;287:2' status='man'/>
<link type='1-1' xtargets='134:1;287:3' status='man'/>
<link type='1-1' xtargets='134:2;287:4' status='man'/>
<link type='1-1' xtargets='134:3;287:5' status='man'/>
<link type='1-1' xtargets='134:4;288:1' status='man'/>
<link type='1-1' xtargets='134:5;289:1' status='man'/>
<link type='1-1' xtargets='134:6;290:1' status='man'/>
<link type='1-0' xtargets='135:1;' status='man'/>
<link type='1-1' xtargets='136:1;291:1' status='man'/>
<link type='1-1' xtargets='136:2;291:2' status='man'/>
<link type='1-1' xtargets='137:1;291:3' status='man'/>
<link type='1-1' xtargets='137:2;291:4' status='man'/>
<link type='1-1' xtargets='137:3;292:1' status='man'/>
<link type='1-1' xtargets='137:4;293:1' status='man'/>
<link type='1-1' xtargets='137:5;294:1' status='man'/>
<link type='1-1' xtargets='137:6;295:1' status='man'/>
<link type='1-1' xtargets='137:7;296:1' status='man'/>
<link type='1-1' xtargets='137:8;297:1' status='man'/>
<link type='1-1' xtargets='137:9;298:1' status='man'/>
<link type='1-1' xtargets='137:10;299:1' status='man'/>
<link type='1-0' xtargets='138:1;' status='man'/>
<link type='1-1' xtargets='139:1;300:1' status='man'/>
<link type='1-1' xtargets='139:2;300:2' status='man'/>
<link type='1-1' xtargets='140:1;300:3' status='man'/>
<link type='1-1' xtargets='140:2;300:4' status='man'/>
<link type='1-1' xtargets='140:3;301:1' status='man'/>
<link type='1-1' xtargets='140:4;301:2' status='man'/>
<link type='1-1' xtargets='140:5;302:1' status='man'/>
<link type='1-1' xtargets='140:6;303:1' status='man'/>
<link type='1-1' xtargets='140:7;304:1' status='man'/>
<link type='1-0' xtargets='141:1;' status='man'/>
<link type='1-1' xtargets='142:1;305:1' status='man'/>
<link type='1-1' xtargets='142:2;305:2' status='man'/>
<link type='1-1' xtargets='143:1;305:3' status='man'/>
<link type='1-1' xtargets='143:2;305:4' status='man'/>
<link type='1-1' xtargets='143:3;305:5' status='man'/>
<link type='1-1' xtargets='143:4;306:1' status='man'/>
<link type='1-1' xtargets='143:5;307:1' status='man'/>
<link type='1-1' xtargets='143:6;308:1' status='man'/>
<link type='1-1' xtargets='143:7;309:1' status='man'/>
<link type='1-1' xtargets='143:8;310:1' status='man'/>
<link type='1-1' xtargets='143:9;311:1' status='man'/>
<link type='1-1' xtargets='144:1;312:1' status='man'/>
<link type='1-1' xtargets='144:2;312:2' status='man'/>
<link type='1-1' xtargets='144:3;312:3' status='man'/>
<link type='1-1' xtargets='145:1;312:4' status='man'/>
<link type='1-1' xtargets='145:2;312:5' status='man'/>
<link type='1-1' xtargets='145:3;313:1' status='man'/>
<link type='1-1' xtargets='145:4;314:1' status='man'/>
<link type='1-1' xtargets='145:5;315:1' status='man'/>
<link type='1-0' xtargets='146:1;' status='man'/>
<link type='1-1' xtargets='147:1;316:1' status='man'/>
<link type='1-1' xtargets='147:2;316:2' status='man'/>
<link type='1-1' xtargets='148:1;316:3' status='man'/>
<link type='1-1' xtargets='148:2;316:4' status='man'/>
<link type='1-1' xtargets='148:3;316:5' status='man'/>
<link type='1-1' xtargets='148:4;317:1' status='man'/>
<link type='1-1' xtargets='148:5;318:1' status='man'/>
<link type='1-1' xtargets='148:6;318:2' status='man'/>
<link type='1-1' xtargets='148:7;318:3' status='man'/>
<link type='1-1' xtargets='148:8;319:1' status='man'/>
<link type='1-1' xtargets='149:1;320:1' status='man'/>
<link type='1-1' xtargets='149:2;321:1' status='man'/>
<link type='1-1' xtargets='149:3;322:1' status='man'/>
<link type='1-1' xtargets='149:4;322:2' status='man'/>
<link type='1-1' xtargets='149:5;322:3' status='man'/>
<link type='1-1' xtargets='150:1;323:1' status='man'/>
<link type='1-1' xtargets='150:2;323:2' status='man'/>
<link type='1-1' xtargets='151:1;324:1' status='man'/>
<link type='1-1' xtargets='151:2;324:2' status='man'/>
<link type='1-1' xtargets='151:3;325:1' status='man'/>
<link type='1-1' xtargets='151:4;326:1' status='man'/>
<link type='1-1' xtargets='151:5;327:1' status='man'/>
<link type='1-0' xtargets='152:1;' status='man'/>
<link type='1-1' xtargets='153:1;328:1' status='man'/>
<link type='1-1' xtargets='153:2;328:2' status='man'/>
<link type='1-1' xtargets='154:1;328:3' status='man'/>
<link type='1-1' xtargets='154:2;328:4' status='man'/>
<link type='1-1' xtargets='154:3;328:5' status='man'/>
<link type='1-1' xtargets='154:4;329:1' status='man'/>
<link type='1-1' xtargets='154:5;330:1' status='man'/>
<link type='1-1' xtargets='154:6;330:2' status='man'/>
<link type='1-1' xtargets='154:7;331:1' status='man'/>
<link type='1-1' xtargets='154:8;332:1' status='man'/>
<link type='1-1' xtargets='154:9;333:1' status='man'/>
<link type='1-1' xtargets='154:10;334:1' status='man'/>
<link type='1-0' xtargets='155:1;' status='man'/>
<link type='1-1' xtargets='156:1;335:1' status='man'/>
<link type='1-1' xtargets='156:2;335:2' status='man'/>
<link type='1-1' xtargets='157:1;335:3' status='man'/>
<link type='1-1' xtargets='157:2;335:4' status='man'/>
<link type='1-1' xtargets='157:3;335:5' status='man'/>
<link type='1-1' xtargets='157:4;335:6' status='man'/>
<link type='1-1' xtargets='157:5;336:1' status='man'/>
<link type='1-1' xtargets='157:6;337:1' status='man'/>
<link type='1-1' xtargets='158:1;338:1' status='man'/>
<link type='1-1' xtargets='158:2;339:1' status='man'/>
<link type='1-1' xtargets='158:3;339:2' status='man'/>
<link type='1-1' xtargets='158:4;340:1' status='man'/>
<link type='1-0' xtargets='159:1;' status='man'/>
<link type='1-1' xtargets='160:1;341:1' status='man'/>
<link type='1-1' xtargets='160:2;341:2' status='man'/>
<link type='1-1' xtargets='161:1;342:1' status='man'/>
<link type='1-1' xtargets='161:2;342:2' status='man'/>
<link type='1-1' xtargets='161:3;343:1' status='man'/>
<link type='1-1' xtargets='161:4;343:2' status='man'/>
<link type='2-2' xtargets='162:1 162:2;344:1 344:2' status='man'/>
<link type='1-1' xtargets='163:1;345:1' status='man'/>
<link type='1-1' xtargets='163:2;345:2' status='man'/>
<link type='1-1' xtargets='164:1;346:1' status='man'/>
<link type='1-1' xtargets='164:2;346:2' status='man'/>
<link type='1-1' xtargets='164:3;346:3' status='man'/>
<link type='1-1' xtargets='165:1;347:1' status='man'/>
<link type='1-1' xtargets='165:2;347:2' status='man'/>
<link type='1-1' xtargets='166:1;348:1' status='man'/>
<link type='1-1' xtargets='167:1;349:1' status='man'/>
<link type='2-2' xtargets='167:2 167:3;349:2 349:3' status='man'/>
<link type='1-1' xtargets='168:1;350:1' status='man'/>
<link type='1-1' xtargets='168:2;351:1' status='man'/>
<link type='1-1' xtargets='168:3;351:2' status='man'/>
<link type='1-1' xtargets='169:1;352:1' status='man'/>
<link type='1-1' xtargets='169:2;353:1' status='man'/>
<link type='1-1' xtargets='169:3;353:2' status='man'/>
<link type='1-1' xtargets='169:4;353:3' status='man'/>
<link type='1-1' xtargets='170:1;354:1' status='man'/>
<link type='1-1' xtargets='170:2;355:1' status='man'/>
<link type='1-1' xtargets='170:3;355:2' status='man'/>
<link type='1-1' xtargets='170:4;355:3' status='man'/>
<link type='1-1' xtargets='170:5;355:4' status='man'/>
<link type='1-1' xtargets='170:6;355:5' status='man'/>
<link type='1-1' xtargets='170:7;355:6' status='man'/>
<link type='1-1' xtargets='170:8;355:7' status='man'/>
<link type='1-1' xtargets='171:1;356:1' status='man'/>
<link type='1-1' xtargets='171:2;356:2' status='man'/>
<link type='1-1' xtargets='171:3;356:3' status='man'/>
<link type='1-1' xtargets='171:4;357:1' status='man'/>
<link type='1-1' xtargets='171:5;357:2' status='man'/>
<link type='1-1' xtargets='171:6;357:3' status='man'/>
<link type='1-1' xtargets='171:7;358:1' status='man'/>
<link type='1-1' xtargets='171:8;358:2' status='man'/>
<link type='1-1' xtargets='172:1;359:1' status='man'/>
<link type='1-1' xtargets='172:2;360:1' status='man'/>
<link type='1-1' xtargets='172:3;361:1' status='man'/>
<link type='1-1' xtargets='173:1;362:1' status='man'/>
<link type='1-1' xtargets='173:2;363:1' status='man'/>
<link type='1-1' xtargets='173:3;364:1' status='man'/>
<link type='1-1' xtargets='173:4;365:1' status='man'/>
<link type='1-1' xtargets='173:5;366:1' status='man'/>
<link type='1-1' xtargets='173:6;367:1' status='man'/>
<link type='1-1' xtargets='173:7;368:1' status='man'/>
<link type='1-1' xtargets='173:8;369:1' status='man'/>
<link type='1-1' xtargets='174:1;370:1' status='man'/>
<link type='1-1' xtargets='174:2;371:1' status='man'/>
<link type='1-1' xtargets='174:3;372:1' status='man'/>
<link type='1-1' xtargets='174:4;373:1' status='man'/>
<link type='1-1' xtargets='174:5;374:1' status='man'/>
<link type='1-1' xtargets='174:6;375:1' status='man'/>
<link type='1-1' xtargets='174:7;375:2' status='man'/>
<link type='1-1' xtargets='174:8;376:1' status='man'/>
<link type='1-1' xtargets='175:1;377:1' status='man'/>
<link type='1-1' xtargets='176:1;378:1' status='man'/>
<link type='1-0' xtargets='177:1;' status='man'/>
<link type='1-1' xtargets='178:1;379:1' status='man'/>
<link type='1-1' xtargets='178:2;379:2' status='man'/>
<link type='1-1' xtargets='179:1;380:1' status='man'/>
<link type='1-1' xtargets='179:2;380:2' status='man'/>
<link type='1-1' xtargets='179:3;381:1' status='man'/>
<link type='0-1' xtargets=';381:2' status='man'/>
<link type='1-1' xtargets='179:4;382:1' status='man'/>
<link type='1-1' xtargets='180:1;383:1' status='man'/>
<link type='1-1' xtargets='180:2;384:1' status='man'/>
<link type='1-1' xtargets='180:3;385:1' status='man'/>
<link type='1-1' xtargets='180:4;385:2' status='man'/>
<link type='1-1' xtargets='180:5;386:1' status='man'/>
<link type='1-1' xtargets='181:1;387:1' status='man'/>
<link type='1-1' xtargets='181:2;388:1' status='man'/>
<link type='1-1' xtargets='181:3;389:1' status='man'/>
<link type='1-1' xtargets='182:1;390:1' status='man'/>
<link type='1-1' xtargets='182:2;391:1' status='man'/>
<link type='1-1' xtargets='182:3;392:1' status='man'/>
<link type='1-1' xtargets='183:1;393:1' status='man'/>
<link type='1-1' xtargets='183:2;394:1' status='man'/>
<link type='1-1' xtargets='183:3;395:1' status='man'/>
<link type='1-1' xtargets='184:1;396:1' status='man'/>
<link type='1-1' xtargets='184:2;397:1' status='man'/>
<link type='1-1' xtargets='184:3;397:2' status='man'/>
<link type='1-1' xtargets='184:4;398:1' status='man'/>
<link type='1-1' xtargets='184:5;399:1' status='man'/>
<link type='1-1' xtargets='184:6;399:2' status='man'/>
<link type='1-1' xtargets='184:7;399:3' status='man'/>
<link type='1-1' xtargets='184:8;399:4' status='man'/>
<link type='1-1' xtargets='185:1;399:5' status='man'/>
<link type='1-1' xtargets='185:2;400:1' status='man'/>
<link type='1-1' xtargets='185:3;400:2' status='man'/>
<link type='1-1' xtargets='185:4;401:1' status='man'/>
<link type='1-1' xtargets='185:5;402:1' status='man'/>
<link type='1-1' xtargets='185:6;403:1' status='man'/>
<link type='1-1' xtargets='185:7;404:1' status='man'/>
<link type='1-1' xtargets='185:8;405:1' status='man'/>
<link type='1-1' xtargets='186:1;406:1' status='man'/>
<link type='1-1' xtargets='186:2;407:1' status='man'/>
<link type='1-1' xtargets='186:3;407:2' status='man'/>
<link type='1-1' xtargets='186:4;408:1' status='man'/>
<link type='1-1' xtargets='186:5;409:1' status='man'/>
<link type='1-1' xtargets='186:6;410:1' status='man'/>
<link type='1-1' xtargets='186:7;411:1' status='man'/>
<link type='1-1' xtargets='186:8;412:1' status='man'/>
<link type='1-1' xtargets='186:9;413:1' status='man'/>
<link type='1-1' xtargets='187:1;414:1' status='man'/>
<link type='1-1' xtargets='187:2;415:1' status='man'/>
<link type='1-1' xtargets='187:3;415:2' status='man'/>
<link type='1-1' xtargets='187:4;416:1' status='man'/>
<link type='1-1' xtargets='187:5;417:1' status='man'/>
<link type='1-1' xtargets='187:6;418:1' status='man'/>
<link type='1-1' xtargets='187:7;419:1' status='man'/>
<link type='1-1' xtargets='188:1;420:1' status='man'/>
<link type='1-1' xtargets='188:2;421:1' status='man'/>
<link type='1-1' xtargets='188:3;421:2' status='man'/>
<link type='1-1' xtargets='188:4;422:1' status='man'/>
<link type='1-1' xtargets='188:5;423:1' status='man'/>
<link type='1-1' xtargets='188:6;424:1' status='man'/>
<link type='1-1' xtargets='188:7;425:1' status='man'/>
<link type='1-1' xtargets='189:1;426:1' status='man'/>
<link type='1-1' xtargets='189:2;427:1' status='man'/>
<link type='1-1' xtargets='189:3;427:2' status='man'/>
<link type='1-1' xtargets='189:4;428:1' status='man'/>
<link type='1-1' xtargets='189:5;429:1' status='man'/>
<link type='1-1' xtargets='189:6;430:1' status='man'/>
<link type='1-1' xtargets='189:7;431:1' status='man'/>
<link type='1-1' xtargets='190:1;432:1' status='man'/>
<link type='1-1' xtargets='190:2;433:1' status='man'/>
<link type='1-1' xtargets='190:3;433:2' status='man'/>
<link type='1-1' xtargets='190:4;434:1' status='man'/>
<link type='1-1' xtargets='190:5;435:1' status='man'/>
<link type='1-1' xtargets='190:6;436:1' status='man'/>
<link type='1-1' xtargets='190:7;437:1' status='man'/>
<link type='1-1' xtargets='190:8;438:1' status='man'/>
<link type='1-1' xtargets='191:1;439:1' status='man'/>
<link type='1-1' xtargets='191:2;440:1' status='man'/>
<link type='1-1' xtargets='191:3;440:2' status='man'/>
<link type='1-1' xtargets='191:4;441:1' status='man'/>
<link type='1-1' xtargets='191:5;442:1' status='man'/>
<link type='1-1' xtargets='191:6;443:1' status='man'/>
<link type='1-1' xtargets='191:7;444:1' status='man'/>
<link type='1-1' xtargets='192:1;445:1' status='man'/>
<link type='1-1' xtargets='192:2;446:1' status='man'/>
<link type='1-1' xtargets='192:3;446:2' status='man'/>
<link type='1-1' xtargets='192:4;447:1' status='man'/>
<link type='1-1' xtargets='192:5;448:1' status='man'/>
<link type='1-1' xtargets='192:6;448:2' status='man'/>
<link type='1-1' xtargets='192:7;449:1' status='man'/>
<link type='1-1' xtargets='192:8;450:1' status='man'/>
<link type='1-1' xtargets='193:1;451:1' status='man'/>
<link type='1-1' xtargets='193:2;452:1' status='man'/>
<link type='1-1' xtargets='193:3;452:2' status='man'/>
<link type='1-1' xtargets='193:4;453:1' status='man'/>
<link type='1-1' xtargets='193:5;454:1' status='man'/>
<link type='1-1' xtargets='193:6;455:1' status='man'/>
<link type='1-1' xtargets='193:7;456:1' status='man'/>
<link type='1-1' xtargets='194:1;457:1' status='man'/>
<link type='1-1' xtargets='194:2;457:2' status='man'/>
<link type='1-1' xtargets='194:3;458:1' status='man'/>
<link type='1-1' xtargets='194:4;459:1' status='man'/>
<link type='1-1' xtargets='195:1;460:1' status='man'/>
<link type='1-0' xtargets='196:1;' status='man'/>
<link type='1-1' xtargets='197:1;461:1' status='man'/>
<link type='1-1' xtargets='197:2;461:2' status='man'/>
<link type='1-1' xtargets='198:1;461:3' status='man'/>
<link type='1-1' xtargets='198:2;461:4' status='man'/>
<link type='1-1' xtargets='198:3;462:1' status='man'/>
<link type='1-1' xtargets='199:1;463:1' status='man'/>
<link type='1-1' xtargets='200:1;464:1' status='man'/>
<link type='1-1' xtargets='201:1;465:1' status='man'/>
<link type='1-1' xtargets='202:1;466:1' status='man'/>
<link type='1-1' xtargets='203:1;467:1' status='man'/>
<link type='1-1' xtargets='204:1;468:1' status='man'/>
<link type='1-1' xtargets='205:1;469:1' status='man'/>
<link type='1-1' xtargets='206:1;470:1' status='man'/>
<link type='1-1' xtargets='207:1;471:1' status='man'/>
<link type='1-1' xtargets='208:1;472:1' status='man'/>
<link type='1-1' xtargets='209:1;473:1' status='man'/>
<link type='1-1' xtargets='210:1;474:1' status='man'/>
<link type='1-1' xtargets='211:1;475:1' status='man'/>
<link type='1-1' xtargets='212:1;476:1' status='man'/>
<link type='1-1' xtargets='213:1;477:1' status='man'/>
<link type='1-1' xtargets='214:1;478:1' status='man'/>
<link type='1-1' xtargets='215:1;479:1' status='man'/>
<link type='1-1' xtargets='216:1;480:1' status='man'/>
<link type='1-1' xtargets='217:1;481:1' status='man'/>
<link type='1-1' xtargets='218:1;482:1' status='man'/>
<link type='1-1' xtargets='219:1;483:1' status='man'/>
<link type='1-1' xtargets='220:1;484:1' status='man'/>
<link type='1-1' xtargets='221:1;485:1' status='man'/>
<link type='1-1' xtargets='222:1;486:1' status='man'/>
<link type='1-1' xtargets='223:1;487:1' status='man'/>
<link type='1-1' xtargets='224:1;488:1' status='man'/>
<link type='1-1' xtargets='225:1;489:1' status='man'/>
<link type='1-1' xtargets='226:1;490:1' status='man'/>
<link type='1-1' xtargets='227:1;491:1' status='man'/>
<link type='1-1' xtargets='228:1;492:1' status='man'/>
<link type='1-1' xtargets='229:1;493:1' status='man'/>
<link type='1-1' xtargets='230:1;494:1' status='man'/>
<link type='1-1' xtargets='231:1;495:1' status='man'/>
<link type='1-1' xtargets='232:1;496:1' status='man'/>
<link type='1-1' xtargets='233:1;497:1' status='man'/>
<link type='1-1' xtargets='234:1;498:1' status='man'/>
<link type='1-1' xtargets='235:1;499:1' status='man'/>
<link type='1-1' xtargets='236:1;500:1' status='man'/>
<link type='1-1' xtargets='237:1;501:1' status='man'/>
<link type='1-1' xtargets='238:1;502:1' status='man'/>
<link type='1-1' xtargets='239:1;503:1' status='man'/>
<link type='1-1' xtargets='240:1;504:1' status='man'/>
<link type='1-1' xtargets='241:1;505:1' status='man'/>
<link type='1-1' xtargets='242:1;506:1' status='man'/>
<link type='1-1' xtargets='243:1;507:1' status='man'/>
<link type='1-1' xtargets='244:1;508:1' status='man'/>
<link type='1-1' xtargets='244:2;509:1' status='man'/>
<link type='1-1' xtargets='244:3;510:1' status='man'/>
<link type='1-1' xtargets='244:4;510:2' status='man'/>
<link type='1-1' xtargets='244:5;511:1' status='man'/>
<link type='1-1' xtargets='244:6;512:1' status='man'/>
<link type='1-1' xtargets='244:7;513:1' status='man'/>
<link type='1-1' xtargets='245:1;513:2' status='man'/>
<link type='1-1' xtargets='245:2;514:1' status='man'/>
<link type='1-1' xtargets='245:3;515:1' status='man'/>
<link type='1-1' xtargets='245:4;515:2' status='man'/>
<link type='1-1' xtargets='245:5;516:1' status='man'/>
<link type='1-1' xtargets='245:6;517:1' status='man'/>
<link type='1-1' xtargets='245:7;518:1' status='man'/>
<link type='1-1' xtargets='245:8;519:1' status='man'/>
<link type='1-1' xtargets='246:1;519:2' status='man'/>
<link type='1-1' xtargets='246:2;520:1' status='man'/>
<link type='1-1' xtargets='246:3;521:1' status='man'/>
<link type='1-1' xtargets='246:4;522:1' status='man'/>
<link type='1-1' xtargets='246:5;523:1' status='man'/>
<link type='1-1' xtargets='246:6;524:1' status='man'/>
<link type='1-1' xtargets='246:7;525:1' status='man'/>
<link type='1-1' xtargets='247:1;525:2' status='man'/>
<link type='1-1' xtargets='247:2;526:1' status='man'/>
<link type='1-1' xtargets='247:3;526:2' status='man'/>
<link type='1-1' xtargets='247:4;527:1' status='man'/>
<link type='1-1' xtargets='247:5;527:2' status='man'/>
<link type='1-1' xtargets='247:6;528:1' status='man'/>
<link type='1-1' xtargets='247:7;528:2' status='man'/>
<link type='1-1' xtargets='247:8;529:1' status='man'/>
<link type='1-1' xtargets='247:9;530:1' status='man'/>
<link type='1-1' xtargets='248:1;531:1' status='man'/>
<link type='1-1' xtargets='248:2;532:1' status='man'/>
<link type='1-1' xtargets='248:3;533:1' status='man'/>
<link type='1-1' xtargets='248:4;533:2' status='man'/>
<link type='1-1' xtargets='249:1;533:3' status='man'/>
<link type='1-1' xtargets='249:2;534:1' status='man'/>
<link type='1-1' xtargets='249:3;535:1' status='man'/>
<link type='0-1' xtargets=';536:1' status='man'/>
<link type='1-0' xtargets='250:1;' status='man'/>
<link type='1-1' xtargets='251:1;536:2' status='man'/>
<link type='1-1' xtargets='251:2;537:1' status='man'/>
<link type='1-1' xtargets='251:3;538:1' status='man'/>
<link type='1-1' xtargets='252:1;539:1' status='man'/>
<link type='1-1' xtargets='252:2;540:1' status='man'/>
<link type='1-1' xtargets='253:1;541:1' status='man'/>
<link type='2-2' xtargets='253:2 253:3;542:1 543:1' status='man'/>
<link type='1-1' xtargets='254:1;544:1' status='man'/>
<link type='1-1' xtargets='254:2;545:1' status='man'/>
<link type='1-1' xtargets='254:3;546:1' status='man'/>
<link type='1-1' xtargets='255:1;547:1' status='man'/>
<link type='1-1' xtargets='255:2;548:1' status='man'/>
<link type='1-1' xtargets='255:3;549:1' status='man'/>
<link type='1-1' xtargets='255:4;550:1' status='man'/>
<link type='1-1' xtargets='255:5;551:1' status='man'/>
<link type='1-1' xtargets='255:6;552:1' status='man'/>
<link type='1-1' xtargets='255:7;553:1' status='man'/>
<link type='1-1' xtargets='255:8;554:1' status='man'/>
<link type='1-1' xtargets='255:9;555:1' status='man'/>
<link type='1-1' xtargets='255:10;556:1' status='man'/>
<link type='1-1' xtargets='255:11;557:1' status='man'/>
<link type='1-1' xtargets='255:12;558:1' status='man'/>
<link type='1-1' xtargets='255:13;559:1' status='man'/>
<link type='1-1' xtargets='256:1;560:1' status='man'/>
<link type='1-1' xtargets='256:2;560:2' status='man'/>
<link type='1-1' xtargets='257:1;560:3' status='man'/>
<link type='1-1' xtargets='257:2;560:4' status='man'/>
<link type='1-1' xtargets='257:3;560:5' status='man'/>
<link type='1-1' xtargets='257:4;560:6' status='man'/>
<link type='1-1' xtargets='257:5;560:7' status='man'/>
<link type='1-1' xtargets='257:6;560:8' status='man'/>
<link type='1-1' xtargets='257:7;560:9' status='man'/>
<link type='1-1' xtargets='257:8;560:10' status='man'/>
<link type='1-1' xtargets='257:9;560:11' status='man'/>
<link type='1-1' xtargets='257:10;560:12' status='man'/>
<link type='1-1' xtargets='257:11;560:13' status='man'/>
<link type='1-1' xtargets='257:12;560:14' status='man'/>
<link type='1-1' xtargets='257:13;560:15' status='man'/>
<link type='1-1' xtargets='257:14;561:1' status='man'/>
<link type='1-1' xtargets='257:15;562:1' status='man'/>
<link type='1-1' xtargets='257:16;563:1' status='man'/>
<link type='1-1' xtargets='258:1;563:2' status='man'/>
<link type='1-1' xtargets='258:2;563:3' status='man'/>
<link type='1-1' xtargets='258:3;564:1' status='man'/>
<link type='1-1' xtargets='258:4;565:1' status='man'/>
<link type='1-1' xtargets='258:5;566:1' status='man'/>
<link type='1-1' xtargets='259:1;567:1' status='man'/>
<link type='1-1' xtargets='259:2;568:1' status='man'/>
<link type='1-1' xtargets='260:1;569:1' status='man'/>
<link type='1-1' xtargets='260:2;569:2' status='man'/>
<link type='1-1' xtargets='260:3;570:1' status='man'/>
<link type='1-1' xtargets='260:4;570:2' status='man'/>
<link type='1-1' xtargets='260:5;570:3' status='man'/>
<link type='1-1' xtargets='260:6;571:1' status='man'/>
<link type='1-1' xtargets='261:1;572:1' status='man'/>
<link type='1-1' xtargets='261:2;573:1' status='man'/>
<link type='1-1' xtargets='261:3;574:1' status='man'/>
<link type='1-1' xtargets='261:4;575:1' status='man'/>
<link type='1-1' xtargets='262:1;576:1' status='man'/>
<link type='1-1' xtargets='262:2;577:1' status='man'/>
<link type='1-1' xtargets='263:1;578:1' status='man'/>
<link type='1-1' xtargets='263:2;578:2' status='man'/>
<link type='1-1' xtargets='263:3;578:3' status='man'/>
<link type='1-1' xtargets='264:1;579:1' status='man'/>
<link type='1-1' xtargets='264:2;579:2' status='man'/>
<link type='1-1' xtargets='264:3;579:3' status='man'/>
<link type='1-1' xtargets='264:4;579:4' status='man'/>
<link type='1-1' xtargets='264:5;579:5' status='man'/>
<link type='1-1' xtargets='264:6;579:6' status='man'/>
<link type='1-1' xtargets='265:1;580:1' status='man'/>
<link type='1-1' xtargets='265:2;580:2' status='man'/>
<link type='1-1' xtargets='266:1;581:1' status='man'/>
<link type='1-0' xtargets='267:1;' status='man'/>
<link type='1-1' xtargets='268:1;582:1' status='auto'/>
</linkGrp>
