<?xml version='1.0' encoding='utf-8'?>
<linkGrp toDoc='Toh_185.en.xml' fromDoc='Toh_185.bo.xml'>
<link type='0-1' xtargets=';1:1' status='man'/>
<link type='2-1' xtargets='1:1 2:1;1:2' status='man'/>
<link type='1-0' xtargets='3:1;' status='man'/>
<link type='0-1' xtargets=';1:3' status='man'/>
<link type='1-1' xtargets='4:1;1:4' status='man'/>
<link type='2-2' xtargets='5:1 5:2;2:1 3:1' status='man'/>
<link type='1-1' xtargets='6:1;4:1' status='man'/>
<link type='1-1' xtargets='6:2;4:2' status='man'/>
<link type='1-1' xtargets='6:3;4:3' status='man'/>
<link type='1-1' xtargets='6:4;4:4' status='man'/>
<link type='1-1' xtargets='6:5;4:5' status='man'/>
<link type='1-1' xtargets='6:6;4:6' status='man'/>
<link type='1-1' xtargets='6:7;4:7' status='man'/>
<link type='1-1' xtargets='6:8;4:8' status='man'/>
<link type='1-1' xtargets='6:9;4:9' status='man'/>
<link type='1-1' xtargets='6:10;4:10' status='man'/>
<link type='2-1' xtargets='6:11 6:12;4:11' status='man'/>
<link type='1-1' xtargets='6:13;4:12' status='man'/>
<link type='1-1' xtargets='6:14;4:13' status='man'/>
<link type='1-1' xtargets='6:15;4:14' status='man'/>
<link type='1-1' xtargets='6:16;4:15' status='man'/>
<link type='1-1' xtargets='6:17;4:16' status='man'/>
<link type='1-1' xtargets='6:18;5:1' status='man'/>
<link type='1-1' xtargets='7:1;6:1' status='man'/>
<link type='1-1' xtargets='7:2;6:2' status='man'/>
<link type='1-1' xtargets='8:1;7:1' status='man'/>
<link type='1-1' xtargets='8:2;8:1' status='man'/>
<link type='1-1' xtargets='8:3;9:1' status='man'/>
<link type='1-1' xtargets='8:4;10:1' status='man'/>
<link type='1-1' xtargets='8:5;11:1' status='man'/>
<link type='1-1' xtargets='8:6;12:1' status='man'/>
<link type='1-1' xtargets='8:7;13:1' status='man'/>
<link type='1-1' xtargets='8:8;14:1' status='man'/>
<link type='1-1' xtargets='8:9;15:1' status='man'/>
<link type='1-1' xtargets='8:10;16:1' status='man'/>
<link type='1-1' xtargets='8:11;17:1' status='man'/>
<link type='1-1' xtargets='8:12;18:1' status='man'/>
<link type='1-1' xtargets='8:13;19:1' status='man'/>
<link type='1-1' xtargets='8:14;20:1' status='man'/>
<link type='1-1' xtargets='9:1;21:1' status='man'/>
<link type='1-1' xtargets='9:3;22:1' status='man'/>
<link type='1-1' xtargets='9:2;23:1' status='man'/>
<link type='1-1' xtargets='9:4;24:1' status='man'/>
<link type='1-1' xtargets='9:5;25:1' status='man'/>
<link type='1-1' xtargets='9:6;26:1' status='man'/>
<link type='1-1' xtargets='9:7;26:2' status='man'/>
<link type='1-1' xtargets='9:8;26:3' status='man'/>
<link type='1-1' xtargets='9:9;26:4' status='man'/>
<link type='1-1' xtargets='9:10;27:1' status='man'/>
<link type='1-1' xtargets='10:1;28:1' status='man'/>
<link type='9-1' xtargets='11:1 11:2 11:3 11:4 11:5 11:6 11:7 11:8 11:9;29:1' status='man'/>
<link type='3-1' xtargets='11:10 11:11 11:12;29:2' status='man'/>
<link type='1-1' xtargets='12:1;30:1' status='man'/>
<link type='1-1' xtargets='12:2;31:1' status='man'/>
<link type='1-1' xtargets='12:3;32:1' status='man'/>
<link type='1-1' xtargets='12:4;33:1' status='man'/>
<link type='1-1' xtargets='12:5;34:1' status='man'/>
<link type='1-1' xtargets='12:6;35:1' status='man'/>
<link type='1-1' xtargets='12:7;36:1' status='man'/>
<link type='1-1' xtargets='13:1;37:1' status='man'/>
<link type='1-1' xtargets='13:2;38:1' status='man'/>
<link type='1-1' xtargets='13:3;39:1' status='man'/>
<link type='1-1' xtargets='13:4;40:1' status='man'/>
<link type='1-1' xtargets='13:5;41:1' status='man'/>
<link type='1-1' xtargets='13:6;42:1' status='man'/>
<link type='1-1' xtargets='13:7;43:1' status='man'/>
<link type='1-1' xtargets='13:8;44:1' status='man'/>
<link type='1-1' xtargets='13:9;45:1' status='man'/>
<link type='1-1' xtargets='13:10;46:1' status='man'/>
<link type='1-1' xtargets='14:1;47:1' status='man'/>
<link type='1-1' xtargets='14:2;48:1' status='man'/>
<link type='1-1' xtargets='14:3;49:1' status='man'/>
<link type='1-1' xtargets='15:1;50:1' status='man'/>
<link type='1-1' xtargets='15:2;51:1' status='man'/>
<link type='1-1' xtargets='15:3;52:1' status='man'/>
<link type='1-1' xtargets='15:4;53:1' status='man'/>
<link type='1-1' xtargets='15:5;54:1' status='man'/>
<link type='1-1' xtargets='15:6;55:1' status='man'/>
<link type='1-1' xtargets='15:7;56:1' status='man'/>
<link type='1-1' xtargets='15:8;57:1' status='man'/>
<link type='1-1' xtargets='15:9;58:1' status='man'/>
<link type='1-1' xtargets='15:10;59:1' status='man'/>
<link type='1-1' xtargets='15:11;60:1' status='man'/>
<link type='1-1' xtargets='15:12;61:1' status='man'/>
<link type='1-1' xtargets='15:13;62:1' status='man'/>
<link type='1-1' xtargets='15:14;63:1' status='man'/>
<link type='1-1' xtargets='15:15;64:1' status='man'/>
<link type='1-1' xtargets='15:16;65:1' status='man'/>
<link type='1-1' xtargets='15:17;66:1' status='man'/>
<link type='1-1' xtargets='15:18;67:1' status='man'/>
<link type='1-1' xtargets='16:1;68:1' status='man'/>
<link type='1-1' xtargets='16:2;69:1' status='man'/>
<link type='1-1' xtargets='16:3;70:1' status='man'/>
<link type='1-1' xtargets='17:1;71:1' status='man'/>
<link type='1-1' xtargets='17:2;72:1' status='man'/>
<link type='1-1' xtargets='17:3;73:1' status='man'/>
<link type='1-1' xtargets='17:4;74:1' status='man'/>
<link type='1-1' xtargets='17:5;75:1' status='man'/>
<link type='1-1' xtargets='17:6;76:1' status='man'/>
<link type='1-1' xtargets='17:7;77:1' status='man'/>
<link type='1-1' xtargets='17:8;78:1' status='man'/>
<link type='1-1' xtargets='17:9;79:1' status='man'/>
<link type='1-1' xtargets='17:10;80:1' status='man'/>
<link type='1-1' xtargets='17:11;81:1' status='man'/>
<link type='1-1' xtargets='18:1;82:1' status='man'/>
<link type='1-1' xtargets='18:2;83:1' status='man'/>
<link type='1-1' xtargets='18:3;84:1' status='man'/>
<link type='1-1' xtargets='19:1;85:1' status='man'/>
<link type='1-1' xtargets='19:2;86:1' status='man'/>
<link type='1-1' xtargets='19:3;87:1' status='man'/>
<link type='1-1' xtargets='19:4;88:1' status='man'/>
<link type='1-1' xtargets='19:5;89:1' status='man'/>
<link type='1-1' xtargets='19:6;90:1' status='man'/>
<link type='1-1' xtargets='19:7;91:1' status='man'/>
<link type='1-1' xtargets='19:8;92:1' status='man'/>
<link type='1-1' xtargets='19:9;93:1' status='man'/>
<link type='1-1' xtargets='19:10;94:1' status='man'/>
<link type='1-1' xtargets='19:11;95:1' status='man'/>
<link type='1-2' xtargets='19:12;96:1 97:1' status='man'/>
<link type='1-1' xtargets='19:13;98:1' status='man'/>
<link type='5-3' xtargets='20:1 20:2 20:3 20:4 20:5;99:1 100:1 100:2' status='man'/>
<link type='1-6' xtargets='20:6;101:1 102:1 103:1 104:1 105:1 106:1' status='man'/>
<link type='1-5' xtargets='20:7;107:1 108:1 109:1 110:1 111:1' status='man'/>
<link type='1-5' xtargets='20:8;112:1 113:1 114:1 115:1 116:1' status='man'/>
<link type='1-1' xtargets='20:9;117:1' status='man'/>
<link type='1-1' xtargets='20:10;118:1' status='man'/>
<link type='1-6' xtargets='21:1;119:1 120:1 121:1 122:1 123:1 124:1' status='man'/>
<link type='1-1' xtargets='21:2;125:1' status='man'/>
<link type='1-1' xtargets='21:3;126:1' status='man'/>
<link type='1-1' xtargets='22:1;127:1' status='man'/>
<link type='2-1' xtargets='22:2 22:3;128:1' status='man'/>
<link type='1-1' xtargets='23:1;129:1' status='man'/>
<link type='1-1' xtargets='23:2;130:1' status='man'/>
<link type='1-1' xtargets='23:3;131:1' status='man'/>
<link type='1-1' xtargets='23:4;132:1' status='man'/>
<link type='1-2' xtargets='24:1;133:1 134:1' status='man'/>
<link type='1-2' xtargets='24:2;135:1 136:1' status='man'/>
<link type='1-1' xtargets='24:3;137:1' status='man'/>
<link type='1-2' xtargets='24:4;138:1 139:1' status='man'/>
<link type='1-1' xtargets='24:5;140:1' status='man'/>
<link type='1-1' xtargets='24:6;141:1' status='man'/>
<link type='1-2' xtargets='24:7;142:1 143:1' status='man'/>
<link type='1-1' xtargets='24:8;144:1' status='man'/>
<link type='2-1' xtargets='24:9 24:10;145:1' status='man'/>
<link type='1-1' xtargets='25:1;146:1' status='man'/>
<link type='1-1' xtargets='25:2;147:1' status='man'/>
<link type='0-1' xtargets=';148:1' status='man'/>
<link type='1-1' xtargets='25:3;148:2' status='man'/>
<link type='1-1' xtargets='25:4;149:1' status='man'/>
<link type='0-1' xtargets=';150:1' status='man'/>
<link type='1-2' xtargets='25:5;150:2 151:1' status='man'/>
<link type='1-1' xtargets='25:6;152:1' status='man'/>
<link type='1-4' xtargets='25:7;153:1 154:1 155:1 156:1' status='man'/>
<link type='1-1' xtargets='26:1;157:1' status='man'/>
<link type='1-3' xtargets='26:2;158:1 159:1 160:1' status='man'/>
<link type='0-1' xtargets=';161:1' status='man'/>
<link type='1-1' xtargets='27:1;161:2' status='man'/>
<link type='1-1' xtargets='27:2;162:1' status='man'/>
<link type='1-1' xtargets='27:3;163:1' status='man'/>
<link type='1-1' xtargets='27:4;164:1' status='man'/>
<link type='1-1' xtargets='27:5;165:1' status='man'/>
<link type='1-1' xtargets='27:6;166:1' status='man'/>
<link type='3-1' xtargets='27:7 27:8 27:9;167:1' status='man'/>
<link type='1-1' xtargets='27:10;168:1' status='man'/>
<link type='1-1' xtargets='27:11;169:1' status='man'/>
<link type='1-1' xtargets='27:12;170:1' status='man'/>
<link type='1-1' xtargets='28:1;171:1' status='man'/>
<link type='1-1' xtargets='28:2;172:1' status='man'/>
<link type='1-1' xtargets='28:3;173:1' status='man'/>
<link type='1-1' xtargets='28:4;174:1' status='man'/>
<link type='1-1' xtargets='29:1;175:1' status='man'/>
<link type='1-1' xtargets='29:2;175:2' status='man'/>
<link type='1-1' xtargets='29:3;175:3' status='man'/>
<link type='1-1' xtargets='30:1;176:1' status='man'/>
<link type='1-1' xtargets='30:2;177:1' status='man'/>
<link type='1-1' xtargets='30:3;178:1' status='man'/>
<link type='1-1' xtargets='30:4;179:1' status='man'/>
<link type='1-1' xtargets='30:5;180:1' status='man'/>
<link type='1-1' xtargets='30:6;181:1' status='man'/>
<link type='1-1' xtargets='30:7;181:2' status='man'/>
<link type='1-1' xtargets='30:8;182:1' status='man'/>
<link type='3-3' xtargets='30:9 30:10 30:11;183:1 183:2 183:3' status='man'/>
<link type='1-1' xtargets='31:1;184:1' status='man'/>
<link type='3-3' xtargets='31:2 31:3 31:4;184:2 184:3 184:4' status='man'/>
<link type='1-1' xtargets='32:1;185:1' status='man'/>
<link type='2-3' xtargets='32:2 32:3;186:1 187:1 188:1' status='man'/>
<link type='1-1' xtargets='32:4;189:1' status='man'/>
<link type='1-1' xtargets='32:5;190:1' status='man'/>
<link type='1-1' xtargets='32:6;191:1' status='man'/>
<link type='1-1' xtargets='32:7;192:1' status='man'/>
<link type='1-1' xtargets='32:8;193:1' status='man'/>
<link type='1-1' xtargets='32:9;194:1' status='man'/>
<link type='1-1' xtargets='32:10;195:1' status='man'/>
<link type='1-1' xtargets='33:1;196:1' status='man'/>
<link type='1-1' xtargets='33:2;197:1' status='man'/>
<link type='1-1' xtargets='33:3;197:2' status='man'/>
<link type='1-1' xtargets='33:4;197:3' status='man'/>
<link type='1-1' xtargets='33:5;197:4' status='man'/>
<link type='1-1' xtargets='33:6;197:5' status='man'/>
<link type='1-1' xtargets='33:7;197:6' status='man'/>
<link type='1-1' xtargets='33:8;197:7' status='man'/>
<link type='1-1' xtargets='33:9;197:8' status='man'/>
<link type='1-1' xtargets='33:10;197:9' status='man'/>
<link type='1-1' xtargets='33:11;197:10' status='man'/>
<link type='1-1' xtargets='33:12;197:11' status='man'/>
<link type='1-1' xtargets='33:13;198:1' status='man'/>
<link type='1-1' xtargets='33:14;198:2' status='man'/>
<link type='1-1' xtargets='33:15;198:3' status='man'/>
<link type='1-1' xtargets='33:16;198:4' status='man'/>
<link type='1-1' xtargets='33:17;198:5' status='man'/>
<link type='1-1' xtargets='33:18;199:1' status='man'/>
<link type='1-1' xtargets='34:1;200:1' status='man'/>
<link type='1-1' xtargets='34:2;200:2' status='man'/>
<link type='1-1' xtargets='34:3;201:1' status='man'/>
<link type='1-1' xtargets='34:4;202:1' status='man'/>
<link type='2-6' xtargets='35:1 35:2;203:1 204:1 205:1 206:1 207:1 208:1' status='man'/>
<link type='2-7' xtargets='35:3 35:4;208:2 209:1 210:1 211:1 212:1 213:1 214:1' status='man'/>
<link type='1-1' xtargets='36:1;215:1' status='man'/>
<link type='1-1' xtargets='36:2;216:1' status='man'/>
<link type='1-1' xtargets='36:3;217:1' status='man'/>
<link type='1-1' xtargets='36:4;218:1' status='man'/>
<link type='1-1' xtargets='37:1;219:1' status='man'/>
<link type='1-1' xtargets='37:2;219:2' status='man'/>
<link type='1-1' xtargets='37:3;220:1' status='man'/>
<link type='1-7' xtargets='38:1;221:1 222:1 223:1 224:1 225:1 226:1 227:1' status='man'/>
<link type='2-2' xtargets='38:2 38:3;228:1 229:1' status='man'/>
<link type='1-1' xtargets='38:4;230:1' status='man'/>
<link type='2-3' xtargets='39:1 39:2;231:1 232:1 233:1' status='man'/>
<link type='1-1' xtargets='40:1;234:1' status='man'/>
<link type='1-3' xtargets='40:2;234:2 235:1 236:1' status='man'/>
<link type='1-1' xtargets='41:1;237:1' status='man'/>
<link type='1-1' xtargets='41:2;238:1' status='man'/>
<link type='1-1' xtargets='41:3;239:1' status='man'/>
<link type='1-1' xtargets='41:4;240:1' status='man'/>
<link type='1-1' xtargets='41:5;241:1' status='man'/>
<link type='2-3' xtargets='41:6 41:7;241:2 242:1 243:1' status='man'/>
<link type='1-1' xtargets='42:1;244:1' status='man'/>
<link type='1-2' xtargets='42:2;245:1 246:1' status='man'/>
<link type='1-2' xtargets='42:3;247:1 248:1' status='man'/>
<link type='1-1' xtargets='42:4;249:1' status='man'/>
<link type='1-2' xtargets='42:5;250:1 251:1' status='man'/>
<link type='1-2' xtargets='42:6;252:1 253:1' status='man'/>
<link type='1-2' xtargets='42:7;254:1 255:1' status='man'/>
<link type='1-2' xtargets='42:8;256:1 257:1' status='man'/>
<link type='1-2' xtargets='42:9;258:1 259:1' status='man'/>
<link type='1-2' xtargets='42:10;260:1 261:1' status='man'/>
<link type='1-2' xtargets='42:11;262:1 263:1' status='man'/>
<link type='1-2' xtargets='42:12;264:1 265:1' status='man'/>
<link type='1-2' xtargets='42:13;266:1 267:1' status='man'/>
<link type='1-2' xtargets='43:1;268:1 269:1' status='man'/>
<link type='1-3' xtargets='44:1;270:1 271:1 272:1' status='man'/>
<link type='1-1' xtargets='45:1;273:1' status='man'/>
<link type='2-2' xtargets='46:1 46:2;274:1 275:1' status='man'/>
<link type='1-1' xtargets='47:1;275:2' status='man'/>
<link type='1-1' xtargets='47:2;276:1' status='man'/>
<link type='1-1' xtargets='47:3;277:1' status='man'/>
<link type='1-1' xtargets='47:4;278:1' status='man'/>
<link type='1-1' xtargets='47:5;279:1' status='man'/>
<link type='1-1' xtargets='47:6;280:1' status='man'/>
<link type='1-1' xtargets='47:7;281:1' status='man'/>
<link type='1-1' xtargets='47:8;282:1' status='man'/>
<link type='1-1' xtargets='47:9;283:1' status='man'/>
<link type='1-1' xtargets='47:10;284:1' status='man'/>
<link type='1-1' xtargets='47:11;285:1' status='man'/>
<link type='1-1' xtargets='47:12;286:1' status='man'/>
<link type='1-1' xtargets='47:13;287:1' status='man'/>
<link type='1-2' xtargets='47:14;288:1 289:1' status='man'/>
<link type='1-2' xtargets='48:1;290:1 291:1' status='man'/>
<link type='1-2' xtargets='49:1;292:1 293:1' status='man'/>
<link type='0-1' xtargets=';294:1' status='man'/>
<link type='1-1' xtargets='50:1;294:2' status='man'/>
<link type='1-2' xtargets='50:2;294:3 295:1' status='man'/>
<link type='2-1' xtargets='50:3 50:4;296:1' status='man'/>
<link type='1-1' xtargets='51:1;297:1' status='man'/>
<link type='1-1' xtargets='51:2;298:1' status='man'/>
<link type='1-1' xtargets='51:3;299:1' status='man'/>
<link type='1-1' xtargets='51:4;300:1' status='man'/>
<link type='1-1' xtargets='51:5;301:1' status='man'/>
<link type='1-1' xtargets='51:6;302:1' status='man'/>
<link type='1-1' xtargets='52:1;303:1' status='man'/>
<link type='1-1' xtargets='52:2;304:1' status='man'/>
<link type='1-1' xtargets='52:3;305:1' status='man'/>
<link type='1-1' xtargets='52:4;306:1' status='man'/>
<link type='1-1' xtargets='52:5;307:1' status='man'/>
<link type='1-2' xtargets='52:6;308:1 309:1' status='man'/>
<link type='1-1' xtargets='52:7;310:1' status='man'/>
<link type='1-3' xtargets='53:1;311:1 312:1 313:1' status='man'/>
<link type='1-1' xtargets='54:1;314:1' status='man'/>
<link type='1-3' xtargets='54:2;314:2 315:1 316:1' status='man'/>
<link type='1-2' xtargets='55:1;317:1 318:1' status='man'/>
<link type='2-2' xtargets='55:2 55:3;319:1 320:1' status='man'/>
<link type='5-5' xtargets='56:1 56:2 56:3 56:4 56:5;321:1 321:2 321:3 321:4 321:5' status='man'/>
<link type='1-1' xtargets='56:6;322:1' status='man'/>
<link type='1-3' xtargets='56:7;322:2 323:1 324:1' status='man'/>
<link type='1-3' xtargets='57:1;325:1 326:1 327:1' status='man'/>
<link type='1-3' xtargets='57:2;327:2 328:1 329:1' status='man'/>
<link type='1-2' xtargets='58:1;330:1 331:1' status='man'/>
<link type='1-3' xtargets='58:2;332:1 333:1 334:1' status='man'/>
<link type='1-2' xtargets='59:1;335:1 336:1' status='man'/>
<link type='1-1' xtargets='59:2;337:1' status='man'/>
<link type='1-1' xtargets='59:3;337:2' status='man'/>
<link type='1-3' xtargets='59:4;337:3 338:1 339:1' status='man'/>
<link type='1-1' xtargets='60:1;340:1' status='man'/>
<link type='1-1' xtargets='60:2;341:1' status='man'/>
<link type='2-2' xtargets='60:3 61:1;342:1 343:1' status='man'/>
<link type='0-1' xtargets=';344:1' status='man'/>
<link type='1-1' xtargets='61:2;344:2' status='man'/>
<link type='1-1' xtargets='61:3;345:1' status='man'/>
<link type='1-1' xtargets='61:4;346:1' status='man'/>
<link type='1-1' xtargets='61:5;347:1' status='man'/>
<link type='1-1' xtargets='61:6;348:1' status='man'/>
<link type='5-4' xtargets='61:7 61:8 61:9 61:10 61:11;349:1 350:1 350:2 350:3' status='man'/>
<link type='1-1' xtargets='61:12;351:1' status='man'/>
<link type='1-2' xtargets='62:1;351:2 352:1' status='man'/>
<link type='1-1' xtargets='62:2;353:1' status='man'/>
<link type='1-1' xtargets='62:3;354:1' status='man'/>
<link type='1-1' xtargets='62:4;355:1' status='man'/>
<link type='1-2' xtargets='63:1;355:2 356:1' status='man'/>
<link type='1-1' xtargets='63:2;357:1' status='man'/>
<link type='2-1' xtargets='64:1 64:2;358:1' status='man'/>
<link type='1-1' xtargets='64:3;359:1' status='man'/>
<link type='2-3' xtargets='64:4 64:5;359:2 360:1 361:1' status='man'/>
<link type='1-1' xtargets='65:1;362:1' status='man'/>
<link type='1-1' xtargets='65:2;363:1' status='man'/>
<link type='1-2' xtargets='66:1;364:1 365:1' status='man'/>
<link type='2-1' xtargets='67:1 67:2;366:1' status='man'/>
<link type='2-1' xtargets='67:3 67:4;367:1' status='man'/>
<link type='2-1' xtargets='67:5 67:6;367:2' status='man'/>
<link type='1-1' xtargets='67:7;367:3' status='man'/>
<link type='2-2' xtargets='68:1 68:2;368:1 369:1' status='man'/>
<link type='1-1' xtargets='69:1;370:1' status='man'/>
<link type='1-2' xtargets='69:2;371:1 372:1' status='man'/>
<link type='1-2' xtargets='69:3;373:1 374:1' status='man'/>
<link type='1-1' xtargets='69:4;375:1' status='man'/>
<link type='1-2' xtargets='69:5;376:1 377:1' status='man'/>
<link type='1-2' xtargets='69:6;378:1 379:1' status='man'/>
<link type='1-1' xtargets='69:7;380:1' status='man'/>
<link type='1-3' xtargets='69:8;380:2 381:1 382:1' status='man'/>
<link type='1-1' xtargets='70:1;383:1' status='man'/>
<link type='2-2' xtargets='70:2 70:3;384:1 385:1' status='man'/>
<link type='1-1' xtargets='71:1;386:1' status='man'/>
<link type='1-1' xtargets='71:2;387:1' status='man'/>
<link type='1-1' xtargets='71:3;388:1' status='man'/>
<link type='1-1' xtargets='71:4;389:1' status='man'/>
<link type='1-1' xtargets='71:5;390:1' status='man'/>
<link type='1-1' xtargets='71:6;391:1' status='man'/>
<link type='1-1' xtargets='71:7;392:1' status='man'/>
<link type='1-1' xtargets='71:8;393:1' status='man'/>
<link type='1-2' xtargets='71:9;394:1 395:1' status='man'/>
<link type='1-1' xtargets='71:10;396:1' status='man'/>
<link type='1-1' xtargets='71:11;397:1' status='man'/>
<link type='1-1' xtargets='71:12;398:1' status='man'/>
<link type='1-2' xtargets='71:13;399:1 400:1' status='man'/>
<link type='1-1' xtargets='72:1;401:1' status='man'/>
<link type='1-2' xtargets='72:2;402:1 403:1' status='man'/>
<link type='2-3' xtargets='73:1 73:2;403:2 404:1 405:1' status='man'/>
<link type='3-3' xtargets='74:1 74:2 74:3;406:1 407:1 407:2' status='man'/>
<link type='1-2' xtargets='74:4;407:3 408:1' status='man'/>
<link type='1-1' xtargets='74:5;409:1' status='man'/>
<link type='1-1' xtargets='74:6;410:1' status='man'/>
<link type='2-3' xtargets='75:1 75:2;410:2 411:1 412:1' status='man'/>
<link type='2-3' xtargets='75:3 75:4;413:1 414:1 415:1' status='man'/>
<link type='1-1' xtargets='76:1;416:1' status='man'/>
<link type='1-1' xtargets='77:1;417:1' status='man'/>
<link type='1-1' xtargets='77:2;418:1' status='man'/>
<link type='1-1' xtargets='78:1;419:1' status='man'/>
<link type='1-1' xtargets='79:1;420:1' status='man'/>
<link type='1-1' xtargets='80:1;421:1' status='man'/>
<link type='1-2' xtargets='81:1;422:1 423:1' status='man'/>
<link type='1-1' xtargets='82:1;424:1' status='man'/>
<link type='1-1' xtargets='83:1;425:1' status='man'/>
<link type='1-1' xtargets='84:1;426:1' status='man'/>
<link type='1-1' xtargets='85:1;427:1' status='man'/>
<link type='1-2' xtargets='86:1;428:1 429:1' status='man'/>
<link type='1-1' xtargets='87:1;430:1' status='man'/>
<link type='1-1' xtargets='88:1;431:1' status='man'/>
<link type='1-1' xtargets='89:1;432:1' status='man'/>
<link type='4-2' xtargets='89:2 89:3 89:4 89:5;433:1 434:1' status='man'/>
<link type='2-2' xtargets='89:6 89:7;434:2 435:1' status='man'/>
<link type='1-1' xtargets='90:1;436:1' status='man'/>
<link type='2-1' xtargets='90:2 90:3;436:2' status='man'/>
<link type='1-1' xtargets='90:4;437:1' status='man'/>
<link type='0-1' xtargets=';438:1' status='man'/>
<link type='1-2' xtargets='91:1;438:2 439:1' status='man'/>
<link type='1-1' xtargets='91:2;440:1' status='man'/>
<link type='1-2' xtargets='91:3;440:2 441:1' status='man'/>
<link type='1-1' xtargets='92:1;442:1' status='man'/>
<link type='1-1' xtargets='92:2;442:2' status='man'/>
<link type='1-1' xtargets='93:1;443:1' status='man'/>
<link type='1-1' xtargets='94:1;444:1' status='man'/>
<link type='1-2' xtargets='94:2;444:2 445:1' status='man'/>
<link type='1-2' xtargets='95:1;446:1 447:1' status='man'/>
<link type='1-1' xtargets='95:2;448:1' status='man'/>
<link type='1-1' xtargets='95:3;449:1' status='man'/>
<link type='1-1' xtargets='95:4;450:1' status='man'/>
<link type='1-1' xtargets='95:5;451:1' status='man'/>
<link type='2-2' xtargets='95:6 95:7;451:2 452:1' status='man'/>
<link type='1-1' xtargets='96:1;453:1' status='man'/>
<link type='1-2' xtargets='96:2;454:1 455:1' status='man'/>
<link type='1-1' xtargets='96:3;456:1' status='man'/>
<link type='1-1' xtargets='96:4;457:1' status='man'/>
<link type='2-1' xtargets='96:5 96:6;458:1' status='man'/>
<link type='2-1' xtargets='97:1 97:2;459:1' status='man'/>
<link type='1-1' xtargets='98:1;460:1' status='man'/>
<link type='2-3' xtargets='98:2 98:3;460:2 461:1 462:1' status='man'/>
<link type='1-1' xtargets='99:1;463:1' status='man'/>
<link type='2-5' xtargets='100:1 100:2;463:2 464:1 465:1 466:1 466:2' status='man'/>
<link type='1-2' xtargets='101:1;467:1 468:1' status='man'/>
<link type='1-2' xtargets='102:1;469:1 470:1' status='man'/>
<link type='1-1' xtargets='103:1;471:1' status='man'/>
<link type='1-1' xtargets='104:1;472:1' status='man'/>
<link type='1-1' xtargets='104:2;473:1' status='man'/>
<link type='1-1' xtargets='104:3;474:1' status='man'/>
<link type='1-1' xtargets='105:1;475:1' status='man'/>
<link type='1-1' xtargets='106:1;476:1' status='man'/>
<link type='2-4' xtargets='107:1 107:2;477:1 478:1 479:1 480:1' status='man'/>
<link type='2-2' xtargets='108:1 109:1;481:1 482:1' status='man'/>
<link type='2-2' xtargets='109:2 109:3;483:1 484:1' status='man'/>
<link type='1-2' xtargets='110:1;485:1 486:1' status='man'/>
<link type='1-1' xtargets='110:2;487:1' status='man'/>
<link type='1-1' xtargets='110:3;488:1' status='man'/>
<link type='1-1' xtargets='110:4;489:1' status='man'/>
<link type='1-1' xtargets='110:5;490:1' status='man'/>
<link type='1-1' xtargets='110:6;491:1' status='man'/>
<link type='1-1' xtargets='110:7;492:1' status='man'/>
<link type='1-1' xtargets='110:8;493:1' status='man'/>
<link type='1-1' xtargets='110:9;494:1' status='man'/>
<link type='1-1' xtargets='111:1;495:1' status='man'/>
<link type='1-1' xtargets='111:2;496:1' status='man'/>
<link type='1-1' xtargets='111:3;497:1' status='man'/>
<link type='1-1' xtargets='111:4;498:1' status='man'/>
<link type='1-1' xtargets='111:5;499:1' status='man'/>
<link type='1-1' xtargets='111:6;500:1' status='man'/>
<link type='1-1' xtargets='111:7;501:1' status='man'/>
<link type='1-1' xtargets='111:8;502:1' status='man'/>
<link type='1-1' xtargets='111:9;503:1' status='man'/>
<link type='1-1' xtargets='111:10;504:1' status='man'/>
<link type='1-1' xtargets='111:11;505:1' status='man'/>
<link type='1-1' xtargets='111:12;506:1' status='man'/>
<link type='1-6' xtargets='112:1;507:1 508:1 509:1 510:1 511:1 512:1' status='man'/>
<link type='1-1' xtargets='112:2;513:1' status='man'/>
<link type='1-1' xtargets='112:3;514:1' status='man'/>
<link type='1-1' xtargets='112:4;515:1' status='man'/>
<link type='1-2' xtargets='113:1;516:1 517:1' status='man'/>
<link type='1-1' xtargets='114:1;518:1' status='man'/>
<link type='1-1' xtargets='114:2;518:2' status='man'/>
<link type='1-1' xtargets='114:3;518:3' status='man'/>
<link type='1-1' xtargets='114:4;518:4' status='man'/>
<link type='1-1' xtargets='114:5;518:5' status='man'/>
<link type='1-1' xtargets='114:6;518:6' status='man'/>
<link type='1-1' xtargets='114:7;518:7' status='man'/>
<link type='1-1' xtargets='114:8;518:8' status='man'/>
<link type='1-1' xtargets='114:9;518:9' status='man'/>
<link type='1-1' xtargets='114:10;518:10' status='man'/>
<link type='1-1' xtargets='114:11;519:1' status='man'/>
<link type='1-2' xtargets='114:12;519:2 520:1' status='man'/>
<link type='1-2' xtargets='114:13;521:1 522:1' status='man'/>
<link type='2-2' xtargets='114:14 114:15;522:2 523:1' status='man'/>
<link type='1-1' xtargets='114:16;523:2' status='man'/>
<link type='1-1' xtargets='114:17;524:1' status='man'/>
<link type='1-1' xtargets='114:18;524:2' status='man'/>
<link type='1-1' xtargets='114:19;524:3' status='man'/>
<link type='1-1' xtargets='114:20;524:4' status='man'/>
<link type='1-1' xtargets='114:21;524:5' status='man'/>
<link type='1-1' xtargets='114:22;525:1' status='man'/>
<link type='1-1' xtargets='114:23;525:2' status='man'/>
<link type='2-2' xtargets='114:24 114:25;526:1 527:1' status='man'/>
<link type='1-1' xtargets='115:1;528:1' status='man'/>
<link type='1-1' xtargets='116:1;529:1' status='man'/>
<link type='1-1' xtargets='116:2;530:1' status='man'/>
<link type='1-1' xtargets='117:1;531:1' status='man'/>
<link type='3-2' xtargets='117:2 117:3 117:4;532:1 533:1' status='man'/>
<link type='1-1' xtargets='118:1;534:1' status='man'/>
<link type='1-1' xtargets='118:2;535:1' status='man'/>
<link type='1-1' xtargets='119:1;535:2' status='man'/>
<link type='1-1' xtargets='119:2;536:1' status='man'/>
<link type='1-1' xtargets='119:3;536:2' status='man'/>
<link type='1-1' xtargets='119:4;536:3' status='man'/>
<link type='1-1' xtargets='119:5;536:4' status='man'/>
<link type='1-1' xtargets='119:6;536:5' status='man'/>
<link type='1-1' xtargets='119:7;536:6' status='man'/>
<link type='1-1' xtargets='119:8;536:7' status='man'/>
<link type='1-1' xtargets='119:9;536:8' status='man'/>
<link type='1-1' xtargets='119:10;536:9' status='man'/>
<link type='1-1' xtargets='119:11;536:10' status='man'/>
<link type='1-1' xtargets='119:12;536:11' status='man'/>
<link type='1-1' xtargets='120:1;537:1' status='man'/>
<link type='1-1' xtargets='120:2;538:1' status='man'/>
<link type='1-1' xtargets='120:3;538:2' status='man'/>
<link type='1-1' xtargets='120:4;539:1' status='man'/>
<link type='1-1' xtargets='120:5;539:2' status='man'/>
<link type='1-1' xtargets='120:6;539:3' status='man'/>
<link type='1-1' xtargets='120:7;539:4' status='man'/>
<link type='1-1' xtargets='120:8;539:5' status='man'/>
<link type='1-1' xtargets='120:9;539:6' status='man'/>
<link type='1-1' xtargets='120:10;539:7' status='man'/>
<link type='1-1' xtargets='120:11;539:8' status='man'/>
<link type='1-1' xtargets='120:12;539:9' status='man'/>
<link type='1-1' xtargets='120:13;539:10' status='man'/>
<link type='2-2' xtargets='121:1 121:2;540:1 541:1' status='man'/>
<link type='1-4' xtargets='121:3;542:1 543:1 544:1 545:1' status='man'/>
<link type='1-1' xtargets='121:4;546:1' status='man'/>
<link type='2-1' xtargets='121:5 121:6;546:2' status='man'/>
<link type='1-3' xtargets='122:1;547:1 548:1 549:1' status='man'/>
<link type='2-2' xtargets='123:1 123:2;550:1 551:1' status='man'/>
<link type='1-1' xtargets='123:3;552:1' status='man'/>
<link type='1-1' xtargets='123:4;553:1' status='man'/>
<link type='1-2' xtargets='124:1;554:1 555:1' status='man'/>
<link type='1-1' xtargets='124:2;556:1' status='man'/>
<link type='1-2' xtargets='124:3;557:1 558:1' status='man'/>
<link type='2-2' xtargets='124:4 124:5;559:1 560:1' status='man'/>
<link type='2-1' xtargets='124:6 124:7;561:1' status='man'/>
<link type='0-1' xtargets=';562:1' status='man'/>
<link type='1-1' xtargets='125:1;562:2' status='man'/>
<link type='1-1' xtargets='125:2;562:3' status='man'/>
<link type='1-1' xtargets='125:3;562:4' status='man'/>
<link type='1-1' xtargets='125:4;562:5' status='man'/>
<link type='1-2' xtargets='125:5;562:6 563:1' status='man'/>
<link type='1-1' xtargets='126:1;564:1' status='man'/>
<link type='1-1' xtargets='126:2;564:2' status='man'/>
<link type='1-1' xtargets='126:3;564:3' status='man'/>
<link type='1-1' xtargets='126:4;564:4' status='man'/>
<link type='1-1' xtargets='126:5;564:5' status='man'/>
<link type='1-1' xtargets='126:6;564:6' status='man'/>
<link type='1-1' xtargets='126:7;564:7' status='man'/>
<link type='1-1' xtargets='126:8;564:8' status='man'/>
<link type='6-7' xtargets='126:9 126:10 126:11 126:12 126:13 126:14;564:9 564:10 564:11 564:12 565:1 565:2 566:1' status='man'/>
<link type='2-1' xtargets='127:1 127:2;566:2' status='man'/>
<link type='2-1' xtargets='128:1 128:2;567:1' status='man'/>
<link type='1-1' xtargets='129:1;568:1' status='man'/>
<link type='1-1' xtargets='130:1;568:2' status='man'/>
<link type='1-1' xtargets='130:2;569:1' status='man'/>
<link type='1-1' xtargets='130:3;570:1' status='man'/>
<link type='1-1' xtargets='130:4;571:1' status='man'/>
<link type='1-1' xtargets='130:5;572:1' status='man'/>
<link type='1-1' xtargets='130:6;573:1' status='man'/>
<link type='1-1' xtargets='130:7;574:1' status='man'/>
<link type='2-1' xtargets='130:8 130:9;575:1' status='man'/>
<link type='1-2' xtargets='131:1;576:1 577:1' status='man'/>
<link type='1-1' xtargets='131:2;578:1' status='man'/>
<link type='1-2' xtargets='131:3;579:1 580:1' status='man'/>
<link type='2-2' xtargets='131:4 131:5;580:2 581:1' status='man'/>
<link type='1-2' xtargets='131:6;582:1 583:1' status='man'/>
<link type='1-1' xtargets='131:7;584:1' status='man'/>
<link type='1-1' xtargets='131:8;585:1' status='man'/>
<link type='1-2' xtargets='132:1;586:1 587:1' status='man'/>
<link type='1-1' xtargets='133:1;588:1' status='man'/>
<link type='1-5' xtargets='133:2;589:1 590:1 591:1 592:1 593:1' status='man'/>
<link type='1-6' xtargets='133:3;594:1 595:1 596:1 597:1 598:1 599:1' status='man'/>
<link type='1-2' xtargets='134:1;600:1 601:1' status='man'/>
<link type='1-1' xtargets='135:1;602:1' status='man'/>
<link type='1-1' xtargets='135:2;602:2' status='man'/>
<link type='1-1' xtargets='135:3;602:3' status='man'/>
<link type='2-1' xtargets='135:4 135:5;602:4' status='man'/>
<link type='1-1' xtargets='135:6;602:5' status='man'/>
<link type='1-1' xtargets='135:7;602:6' status='man'/>
<link type='1-1' xtargets='135:8;602:7' status='man'/>
<link type='1-1' xtargets='135:9;602:8' status='man'/>
<link type='1-1' xtargets='135:10;602:9' status='man'/>
<link type='1-1' xtargets='135:11;602:10' status='man'/>
<link type='3-1' xtargets='135:12 135:13 135:14;602:11' status='man'/>
<link type='1-1' xtargets='135:15;602:12' status='man'/>
<link type='1-2' xtargets='136:1;602:13 603:1' status='man'/>
<link type='1-1' xtargets='137:1;603:2' status='man'/>
<link type='1-1' xtargets='137:2;604:1' status='man'/>
<link type='1-1' xtargets='137:3;605:1' status='man'/>
<link type='1-1' xtargets='137:4;606:1' status='man'/>
<link type='1-1' xtargets='137:5;607:1' status='man'/>
<link type='1-1' xtargets='137:6;608:1' status='man'/>
<link type='1-1' xtargets='137:7;609:1' status='man'/>
<link type='1-1' xtargets='137:8;610:1' status='man'/>
<link type='1-1' xtargets='137:9;611:1' status='man'/>
<link type='1-1' xtargets='137:10;612:1' status='man'/>
<link type='1-1' xtargets='137:11;613:1' status='man'/>
<link type='1-1' xtargets='137:12;614:1' status='man'/>
<link type='1-1' xtargets='137:13;615:1' status='man'/>
<link type='1-1' xtargets='137:14;616:1' status='man'/>
<link type='1-1' xtargets='137:15;617:1' status='man'/>
<link type='1-1' xtargets='137:16;618:1' status='man'/>
<link type='1-1' xtargets='137:17;619:1' status='man'/>
<link type='1-1' xtargets='137:18;620:1' status='man'/>
<link type='1-1' xtargets='137:19;621:1' status='man'/>
<link type='1-1' xtargets='137:20;622:1' status='man'/>
<link type='1-1' xtargets='138:1;623:1' status='man'/>
<link type='1-1' xtargets='138:2;623:2' status='man'/>
<link type='1-1' xtargets='138:3;624:1' status='man'/>
<link type='1-1' xtargets='138:4;625:1' status='man'/>
<link type='1-1' xtargets='139:1;626:1' status='man'/>
<link type='1-1' xtargets='139:2;627:1' status='man'/>
<link type='1-1' xtargets='139:3;628:1' status='man'/>
<link type='1-2' xtargets='140:1;629:1 630:1' status='man'/>
<link type='1-1' xtargets='140:2;631:1' status='man'/>
<link type='1-1' xtargets='141:1;632:1' status='man'/>
<link type='1-1' xtargets='141:2;633:1' status='man'/>
<link type='1-1' xtargets='141:3;633:2' status='man'/>
<link type='2-1' xtargets='141:4 141:5;633:3' status='man'/>
<link type='1-1' xtargets='142:1;634:1' status='man'/>
<link type='1-1' xtargets='142:2;635:1' status='man'/>
<link type='1-1' xtargets='142:3;635:2' status='man'/>
<link type='1-1' xtargets='142:4;635:3' status='man'/>
<link type='1-1' xtargets='142:5;635:4' status='man'/>
<link type='1-1' xtargets='142:6;635:5' status='man'/>
<link type='1-1' xtargets='142:7;635:6' status='man'/>
<link type='1-1' xtargets='142:8;635:7' status='man'/>
<link type='1-1' xtargets='142:9;635:8' status='man'/>
<link type='1-1' xtargets='142:10;635:9' status='man'/>
<link type='1-3' xtargets='142:11;636:1 637:1 638:1' status='man'/>
<link type='1-1' xtargets='143:1;639:1' status='man'/>
<link type='1-1' xtargets='143:2;640:1' status='man'/>
<link type='1-1' xtargets='143:3;640:2' status='man'/>
<link type='1-1' xtargets='143:4;640:3' status='man'/>
<link type='1-1' xtargets='143:5;640:4' status='man'/>
<link type='1-1' xtargets='143:6;640:5' status='man'/>
<link type='1-1' xtargets='143:7;640:6' status='man'/>
<link type='1-1' xtargets='143:8;640:7' status='man'/>
<link type='1-1' xtargets='143:9;640:8' status='man'/>
<link type='1-1' xtargets='143:10;640:9' status='man'/>
<link type='1-1' xtargets='143:11;640:10' status='man'/>
<link type='1-1' xtargets='143:12;641:1' status='man'/>
<link type='1-1' xtargets='143:13;642:1' status='man'/>
<link type='1-1' xtargets='143:14;643:1' status='man'/>
<link type='1-1' xtargets='143:15;643:2' status='man'/>
<link type='1-1' xtargets='144:1;644:1' status='man'/>
<link type='1-1' xtargets='144:2;644:2' status='man'/>
<link type='2-1' xtargets='144:3 144:4;644:3' status='man'/>
<link type='1-1' xtargets='144:5;644:4' status='man'/>
<link type='1-2' xtargets='144:6;644:5 645:1' status='man'/>
<link type='2-2' xtargets='145:1 145:2;646:1 647:1' status='man'/>
<link type='1-1' xtargets='145:3;648:1' status='man'/>
<link type='1-1' xtargets='145:4;648:2' status='man'/>
<link type='1-1' xtargets='145:5;649:1' status='man'/>
<link type='1-1' xtargets='145:6;650:1' status='man'/>
<link type='1-1' xtargets='145:7;651:1' status='man'/>
<link type='1-1' xtargets='145:8;652:1' status='man'/>
<link type='1-1' xtargets='145:9;653:1' status='man'/>
<link type='1-1' xtargets='146:1;654:1' status='man'/>
<link type='1-1' xtargets='146:2;655:1' status='man'/>
<link type='0-1' xtargets=';655:2' status='man'/>
<link type='1-1' xtargets='146:3;656:1' status='man'/>
<link type='1-1' xtargets='147:1;657:1' status='man'/>
<link type='1-1' xtargets='147:2;658:1' status='man'/>
<link type='0-1' xtargets=';658:2' status='man'/>
<link type='1-1' xtargets='147:3;659:1' status='man'/>
<link type='1-1' xtargets='148:1;660:1' status='man'/>
<link type='1-1' xtargets='148:2;660:2' status='man'/>
<link type='1-1' xtargets='148:3;660:3' status='man'/>
<link type='1-1' xtargets='148:4;660:4' status='man'/>
<link type='1-1' xtargets='148:5;660:5' status='man'/>
<link type='1-1' xtargets='148:6;660:6' status='man'/>
<link type='1-1' xtargets='148:7;660:7' status='man'/>
<link type='1-1' xtargets='148:8;660:8' status='man'/>
<link type='1-1' xtargets='148:9;660:9' status='man'/>
<link type='2-1' xtargets='148:10 148:11;660:10' status='man'/>
<link type='1-1' xtargets='149:1;660:11' status='man'/>
<link type='1-1' xtargets='149:2;661:1' status='man'/>
<link type='1-1' xtargets='150:1;662:1' status='man'/>
<link type='1-2' xtargets='150:2;663:1 664:1' status='man'/>
<link type='0-1' xtargets=';665:1' status='man'/>
<link type='1-1' xtargets='150:3;665:2' status='man'/>
<link type='1-1' xtargets='151:1;666:1' status='man'/>
<link type='1-1' xtargets='151:2;667:1' status='man'/>
<link type='1-1' xtargets='151:3;668:1' status='man'/>
<link type='1-1' xtargets='151:4;669:1' status='man'/>
<link type='1-1' xtargets='151:5;670:1' status='man'/>
<link type='1-1' xtargets='151:6;671:1' status='man'/>
<link type='2-3' xtargets='151:7 151:8;672:1 673:1 673:2' status='man'/>
<link type='1-1' xtargets='151:9;674:1' status='man'/>
<link type='1-1' xtargets='151:10;675:1' status='man'/>
<link type='1-1' xtargets='151:11;676:1' status='man'/>
<link type='1-1' xtargets='151:12;677:1' status='man'/>
<link type='1-1' xtargets='151:13;678:1' status='man'/>
<link type='1-1' xtargets='151:14;679:1' status='man'/>
<link type='1-1' xtargets='151:15;680:1' status='man'/>
<link type='1-1' xtargets='151:16;681:1' status='man'/>
<link type='1-1' xtargets='151:17;681:2' status='man'/>
<link type='1-1' xtargets='151:18;682:1' status='man'/>
<link type='1-1' xtargets='151:19;683:1' status='man'/>
<link type='1-3' xtargets='151:20;684:1 684:2 685:1' status='man'/>
<link type='1-1' xtargets='151:21;686:1' status='man'/>
<link type='1-1' xtargets='152:1;687:1' status='man'/>
<link type='1-3' xtargets='152:2;687:2 688:1 689:1' status='man'/>
<link type='1-1' xtargets='152:3;690:1' status='man'/>
<link type='1-3' xtargets='152:4;690:2 691:1 692:1' status='man'/>
<link type='1-1' xtargets='153:1;693:1' status='man'/>
<link type='1-3' xtargets='153:2;693:2 694:1 695:1' status='man'/>
<link type='1-1' xtargets='153:3;696:1' status='man'/>
<link type='1-4' xtargets='153:4;696:2 697:1 698:1 699:1' status='man'/>
<link type='1-1' xtargets='154:1;700:1' status='man'/>
<link type='1-1' xtargets='155:1;701:1' status='man'/>
<link type='1-1' xtargets='156:1;702:1' status='man'/>
<link type='1-1' xtargets='156:2;703:1' status='man'/>
<link type='1-1' xtargets='156:3;704:1' status='man'/>
<link type='1-1' xtargets='156:4;705:1' status='man'/>
<link type='1-1' xtargets='156:5;706:1' status='man'/>
<link type='1-3' xtargets='157:1;707:1 708:1 709:1' status='man'/>
<link type='1-1' xtargets='158:1;710:1' status='man'/>
<link type='1-2' xtargets='158:2;711:1 711:2' status='man'/>
<link type='1-1' xtargets='158:3;712:1' status='man'/>
<link type='1-1' xtargets='158:4;713:1' status='man'/>
<link type='1-1' xtargets='158:5;714:1' status='man'/>
<link type='1-1' xtargets='158:6;715:1' status='man'/>
<link type='1-1' xtargets='158:7;716:1' status='man'/>
<link type='1-1' xtargets='158:8;717:1' status='man'/>
<link type='1-1' xtargets='158:9;718:1' status='man'/>
<link type='1-3' xtargets='158:10;719:1 720:1 721:1' status='man'/>
<link type='1-2' xtargets='159:1;722:1 723:1' status='man'/>
<link type='1-3' xtargets='159:2;723:2 724:1 725:1' status='man'/>
<link type='1-3' xtargets='160:1;726:1 727:1 728:1' status='man'/>
<link type='1-3' xtargets='160:2;728:2 729:1 730:1' status='man'/>
<link type='1-1' xtargets='161:1;731:1' status='man'/>
<link type='1-2' xtargets='161:2;732:1 733:1' status='man'/>
<link type='1-2' xtargets='161:3;734:1 735:1' status='man'/>
<link type='1-1' xtargets='161:4;736:1' status='man'/>
<link type='1-1' xtargets='161:5;737:1' status='man'/>
<link type='1-1' xtargets='161:6;738:1' status='man'/>
<link type='1-1' xtargets='161:7;738:2' status='man'/>
<link type='2-3' xtargets='161:8 161:9;738:3 739:1 740:1' status='man'/>
<link type='1-1' xtargets='162:1;741:1' status='man'/>
<link type='1-2' xtargets='162:2;742:1 743:1' status='man'/>
<link type='1-1' xtargets='162:3;743:2' status='man'/>
<link type='1-1' xtargets='162:4;744:1' status='man'/>
<link type='1-1' xtargets='162:5;745:1' status='man'/>
<link type='1-1' xtargets='162:6;746:1' status='man'/>
<link type='1-1' xtargets='162:7;747:1' status='man'/>
<link type='1-1' xtargets='162:8;748:1' status='man'/>
<link type='1-1' xtargets='162:9;749:1' status='man'/>
<link type='2-2' xtargets='162:10 162:11;749:2 750:1' status='man'/>
<link type='1-1' xtargets='163:1;751:1' status='man'/>
<link type='1-1' xtargets='164:1;752:1' status='man'/>
<link type='1-1' xtargets='164:2;753:1' status='man'/>
<link type='1-2' xtargets='164:3;754:1 755:1' status='man'/>
<link type='2-3' xtargets='164:4 164:5;755:2 756:1 757:1' status='man'/>
<link type='1-1' xtargets='164:6;758:1' status='man'/>
<link type='1-1' xtargets='164:7;759:1' status='man'/>
<link type='2-2' xtargets='164:8 164:9;760:1 761:1' status='man'/>
<link type='1-2' xtargets='165:1;762:1 763:1' status='man'/>
<link type='1-1' xtargets='165:2;763:2' status='man'/>
<link type='1-1' xtargets='165:3;764:1' status='man'/>
<link type='1-1' xtargets='165:4;765:1' status='man'/>
<link type='1-2' xtargets='166:1;766:1 767:1' status='man'/>
<link type='1-1' xtargets='166:2;768:1' status='man'/>
<link type='1-1' xtargets='166:3;769:1' status='man'/>
<link type='1-1' xtargets='166:4;770:1' status='man'/>
<link type='1-1' xtargets='166:5;771:1' status='man'/>
<link type='1-2' xtargets='167:1;772:1 773:1' status='man'/>
<link type='1-1' xtargets='167:2;773:2' status='man'/>
<link type='3-5' xtargets='167:3 167:4 167:5;773:3 774:1 774:2 774:3 774:4' status='man'/>
<link type='2-1' xtargets='167:6 167:7;775:1' status='man'/>
<link type='2-1' xtargets='167:8 167:9;776:1' status='man'/>
<link type='1-2' xtargets='167:10;776:2 777:1' status='man'/>
<link type='1-1' xtargets='168:1;778:1' status='man'/>
<link type='1-1' xtargets='168:2;779:1' status='man'/>
<link type='1-1' xtargets='168:3;780:1' status='man'/>
<link type='1-1' xtargets='168:4;781:1' status='man'/>
<link type='1-1' xtargets='168:5;782:1' status='man'/>
<link type='1-1' xtargets='168:6;783:1' status='man'/>
<link type='1-1' xtargets='168:7;784:1' status='man'/>
<link type='1-1' xtargets='168:8;785:1' status='man'/>
<link type='1-1' xtargets='168:9;786:1' status='man'/>
<link type='1-1' xtargets='168:10;787:1' status='man'/>
<link type='1-1' xtargets='168:11;788:1' status='man'/>
<link type='1-1' xtargets='168:12;789:1' status='man'/>
<link type='1-1' xtargets='168:13;790:1' status='man'/>
<link type='1-1' xtargets='169:1;791:1' status='man'/>
<link type='1-1' xtargets='169:2;791:2' status='man'/>
<link type='1-1' xtargets='169:3;791:3' status='man'/>
<link type='1-1' xtargets='169:4;791:4' status='man'/>
<link type='1-1' xtargets='169:5;791:5' status='man'/>
<link type='1-1' xtargets='169:6;791:6' status='man'/>
<link type='1-1' xtargets='169:7;791:7' status='man'/>
<link type='1-1' xtargets='169:8;791:8' status='man'/>
<link type='1-1' xtargets='169:9;791:9' status='man'/>
<link type='1-1' xtargets='169:10;791:10' status='man'/>
<link type='1-1' xtargets='169:11;791:11' status='man'/>
<link type='1-1' xtargets='169:12;791:12' status='man'/>
<link type='1-1' xtargets='169:13;791:13' status='man'/>
<link type='1-1' xtargets='169:14;791:14' status='man'/>
<link type='1-1' xtargets='169:15;791:15' status='man'/>
<link type='1-1' xtargets='169:16;791:16' status='man'/>
<link type='1-1' xtargets='169:17;791:17' status='man'/>
<link type='1-1' xtargets='169:18;791:18' status='man'/>
<link type='1-1' xtargets='169:19;791:19' status='man'/>
<link type='1-1' xtargets='169:20;791:20' status='man'/>
<link type='1-1' xtargets='169:21;791:21' status='man'/>
<link type='1-1' xtargets='169:22;791:22' status='man'/>
<link type='1-1' xtargets='169:23;791:23' status='man'/>
<link type='1-1' xtargets='169:24;791:24' status='man'/>
<link type='1-1' xtargets='169:25;791:25' status='man'/>
<link type='1-1' xtargets='169:26;791:26' status='man'/>
<link type='1-1' xtargets='169:27;791:27' status='man'/>
<link type='1-1' xtargets='169:28;791:28' status='man'/>
<link type='1-1' xtargets='169:29;791:29' status='man'/>
<link type='1-1' xtargets='169:30;791:30' status='man'/>
<link type='1-1' xtargets='169:31;791:31' status='man'/>
<link type='1-1' xtargets='169:32;791:32' status='man'/>
<link type='1-1' xtargets='169:33;791:33' status='man'/>
<link type='1-1' xtargets='169:34;791:34' status='man'/>
<link type='1-1' xtargets='169:35;791:35' status='man'/>
<link type='1-1' xtargets='169:36;791:36' status='man'/>
<link type='1-1' xtargets='169:37;791:37' status='man'/>
<link type='1-1' xtargets='169:38;791:38' status='man'/>
<link type='1-1' xtargets='169:39;791:39' status='man'/>
<link type='1-1' xtargets='169:40;791:40' status='man'/>
<link type='1-1' xtargets='169:41;791:41' status='man'/>
<link type='1-1' xtargets='169:42;791:42' status='man'/>
<link type='1-1' xtargets='169:43;791:43' status='man'/>
<link type='1-1' xtargets='169:44;791:44' status='man'/>
<link type='1-1' xtargets='169:45;791:45' status='man'/>
<link type='1-1' xtargets='169:46;791:46' status='man'/>
<link type='1-1' xtargets='169:47;791:47' status='man'/>
<link type='1-1' xtargets='169:48;792:1' status='man'/>
<link type='1-1' xtargets='170:1;792:2' status='man'/>
<link type='1-1' xtargets='170:2;792:3' status='man'/>
<link type='1-1' xtargets='170:3;792:4' status='man'/>
<link type='1-1' xtargets='170:4;792:5' status='man'/>
<link type='1-1' xtargets='170:5;792:6' status='man'/>
<link type='1-1' xtargets='170:6;792:7' status='man'/>
<link type='1-1' xtargets='170:7;792:8' status='man'/>
<link type='1-1' xtargets='170:8;792:9' status='man'/>
<link type='1-1' xtargets='170:9;792:10' status='man'/>
<link type='1-1' xtargets='170:10;792:11' status='man'/>
<link type='1-1' xtargets='170:11;792:12' status='man'/>
<link type='1-1' xtargets='170:12;793:1' status='man'/>
<link type='1-1' xtargets='171:1;793:2' status='man'/>
<link type='1-1' xtargets='171:2;793:3' status='man'/>
<link type='1-1' xtargets='171:3;793:4' status='man'/>
<link type='1-1' xtargets='171:4;793:5' status='man'/>
<link type='1-1' xtargets='171:5;793:6' status='man'/>
<link type='1-2' xtargets='172:1;793:7 794:1' status='man'/>
<link type='1-1' xtargets='172:2;795:1' status='man'/>
<link type='1-1' xtargets='173:1;796:1' status='man'/>
<link type='1-1' xtargets='173:2;797:1' status='man'/>
<link type='0-1' xtargets=';797:2' status='man'/>
<link type='1-1' xtargets='174:1;797:3' status='man'/>
<link type='1-2' xtargets='174:2;798:1 799:1' status='man'/>
<link type='1-1' xtargets='174:3;800:1' status='man'/>
<link type='1-1' xtargets='174:4;800:2' status='man'/>
<link type='1-1' xtargets='174:5;800:3' status='man'/>
<link type='1-2' xtargets='174:6;800:4 801:1' status='man'/>
<link type='1-2' xtargets='174:7;801:2 802:1' status='man'/>
<link type='1-3' xtargets='174:8;802:2 803:1 804:1' status='man'/>
<link type='1-1' xtargets='175:1;805:1' status='man'/>
<link type='1-1' xtargets='176:1;806:1' status='man'/>
<link type='1-2' xtargets='176:2;807:1 808:1' status='man'/>
<link type='4-5' xtargets='177:1 177:2 177:3 177:4;809:1 809:2 809:3 809:4 810:1' status='man'/>
<link type='1-1' xtargets='177:5;810:2' status='man'/>
<link type='1-2' xtargets='178:1;810:3 811:1' status='man'/>
<link type='1-2' xtargets='178:2;812:1 813:1' status='man'/>
<link type='1-2' xtargets='178:3;814:1 815:1' status='man'/>
<link type='1-2' xtargets='178:4;816:1 817:1' status='man'/>
<link type='1-1' xtargets='179:1;818:1' status='man'/>
<link type='3-5' xtargets='179:2 179:3 179:4;818:2 819:1 819:2 819:3 819:4' status='man'/>
<link type='1-1' xtargets='180:1;820:1' status='man'/>
<link type='1-2' xtargets='181:1;821:1 822:1' status='man'/>
<link type='2-2' xtargets='182:1 182:2;823:1 824:1' status='man'/>
<link type='1-2' xtargets='182:3;825:1 826:1' status='man'/>
<link type='1-2' xtargets='182:4;827:1 828:1' status='man'/>
<link type='1-1' xtargets='183:1;829:1' status='man'/>
<link type='1-2' xtargets='184:1;830:1 831:1' status='man'/>
<link type='2-1' xtargets='185:1 185:2;832:1' status='man'/>
<link type='1-2' xtargets='185:3;832:2 833:1' status='man'/>
<link type='1-1' xtargets='185:4;834:1' status='man'/>
<link type='1-2' xtargets='185:5;834:2 835:1' status='man'/>
<link type='1-1' xtargets='185:6;836:1' status='man'/>
<link type='0-1' xtargets=';837:1' status='plain'/>
<link type='1-3' xtargets='186:1;838:1 839:1 840:1' status='man'/>
<link type='1-1' xtargets='187:1;841:1' status='man'/>
<link type='1-0' xtargets='188:1;' status='man'/>
<link type='1-1' xtargets='189:1;842:1' status='auto'/>
</linkGrp>
